{"bIdx":43545,"bType":"thm","type":"","name":"frege123","params":"setvar s0, class c0, class c1, class c2, class c3, class c4, class c5","body":["|- wi(wi(wal(s0, wi(wbr(c0, c1, cv(s0)), wbr(c2, cun(cfv(ctcl, c1), cid), cv(s0)))), wi(wbr(c0, cfv(ctcl, c1), c3), wbr(c2, cun(cfv(ctcl, c1), cid), c3))), wi(wfun(ccnv(ccnv(c1))), wi(wbr(c0, c1, c2), wi(wbr(c0, cfv(ctcl, c1), c3), wbr(c2, cun(cfv(ctcl, c1), cid), c3)))))","-| wcel(c2, c4)","-| wcel(c0, c5)","-| diffsc(s0, c0)","-| diffsc(s0, c1)","-| diffsc(s0, c2)"],"bodyPretty":["⊢ ((∀(s0,(c0[c1]s0 → c2[((t+ ` c1)⋃ =)]s0))→(c0[(t+ ` c1)]c3 → c2[((t+ ` c1)⋃ =)]c3))→(Fun(`' `' c1)→(c0[c1]c2 →(c0[(t+ ` c1)]c3 → c2[((t+ ` c1)⋃ =)]c3))))","⊣ c2 ∈ c4","⊣ c0 ∈ c5","⊣ d(s0, c0)","⊣ d(s0, c1)","⊣ d(s0, c2)"],"proof":[{"stmt":{"origin":"ax-mp(wi(wi(wal(s0, wi(wbr(c0, c1, cv(s0)), wbr(c2, cun(cfv(ctcl, c1), cid), cv(s0)))), wi(wbr(c0, cfv(ctcl, c1), c3), wbr(c2, cun(cfv(ctcl, c1), cid), c3))), wi(wfun(ccnv(ccnv(c1))), wi(wbr(c0, c1, c2), wi(wbr(c0, cfv(ctcl, c1), c3), wbr(c2, cun(cfv(ctcl, c1), cid), c3))))), wi(wfun(ccnv(ccnv(c1))), wi(wbr(c0, c1, c2), wal(s0, wi(wbr(c0, c1, cv(s0)), wbr(c2, cun(cfv(ctcl, c1), cid), cv(s0)))))))","pretty":"ax-mp(((∀(s0,(c0[c1]s0 → c2[((t+ ` c1)⋃ =)]s0))→(c0[(t+ ` c1)]c3 → c2[((t+ ` c1)⋃ =)]c3))→(Fun(`' `' c1)→(c0[c1]c2 →(c0[(t+ ` c1)]c3 → c2[((t+ ` c1)⋃ =)]c3)))), (Fun(`' `' c1)→(c0[c1]c2 → ∀(s0,(c0[c1]s0 → c2[((t+ ` c1)⋃ =)]s0)))))"},"body":{"origin":"|- wi(wi(wal(s0, wi(wbr(c0, c1, cv(s0)), wbr(c2, cun(cfv(ctcl, c1), cid), cv(s0)))), wi(wbr(c0, cfv(ctcl, c1), c3), wbr(c2, cun(cfv(ctcl, c1), cid), c3))), wi(wfun(ccnv(ccnv(c1))), wi(wbr(c0, c1, c2), wi(wbr(c0, cfv(ctcl, c1), c3), wbr(c2, cun(cfv(ctcl, c1), cid), c3)))))\n-| wi(wfun(ccnv(ccnv(c1))), wi(wbr(c0, c1, c2), wal(s0, wi(wbr(c0, c1, cv(s0)), wbr(c2, cun(cfv(ctcl, c1), cid), cv(s0))))))\n-| wi(wi(wfun(ccnv(ccnv(c1))), wi(wbr(c0, c1, c2), wal(s0, wi(wbr(c0, c1, cv(s0)), wbr(c2, cun(cfv(ctcl, c1), cid), cv(s0)))))), wi(wi(wal(s0, wi(wbr(c0, c1, cv(s0)), wbr(c2, cun(cfv(ctcl, c1), cid), cv(s0)))), wi(wbr(c0, cfv(ctcl, c1), c3), wbr(c2, cun(cfv(ctcl, c1), cid), c3))), wi(wfun(ccnv(ccnv(c1))), wi(wbr(c0, c1, c2), wi(wbr(c0, cfv(ctcl, c1), c3), wbr(c2, cun(cfv(ctcl, c1), cid), c3))))))","pretty":"⊢ ((∀(s0,(c0[c1]s0 → c2[((t+ ` c1)⋃ =)]s0))→(c0[(t+ ` c1)]c3 → c2[((t+ ` c1)⋃ =)]c3))→(Fun(`' `' c1)→(c0[c1]c2 →(c0[(t+ ` c1)]c3 → c2[((t+ ` c1)⋃ =)]c3))))\n⊣ (Fun(`' `' c1)→(c0[c1]c2 → ∀(s0,(c0[c1]s0 → c2[((t+ ` c1)⋃ =)]s0))))\n⊣ ((Fun(`' `' c1)→(c0[c1]c2 → ∀(s0,(c0[c1]s0 → c2[((t+ ` c1)⋃ =)]s0))))→((∀(s0,(c0[c1]s0 → c2[((t+ ` c1)⋃ =)]s0))→(c0[(t+ ` c1)]c3 → c2[((t+ ` c1)⋃ =)]c3))→(Fun(`' `' c1)→(c0[c1]c2 →(c0[(t+ ` c1)]c3 → c2[((t+ ` c1)⋃ =)]c3)))))"},"cumulated":{"origin":"|- wi(wi(wal(s0, wi(wbr(c0, c1, cv(s0)), wbr(c2, cun(cfv(ctcl, c1), cid), cv(s0)))), wi(wbr(c0, cfv(ctcl, c1), c3), wbr(c2, cun(cfv(ctcl, c1), cid), c3))), wi(wfun(ccnv(ccnv(c1))), wi(wbr(c0, c1, c2), wi(wbr(c0, cfv(ctcl, c1), c3), wbr(c2, cun(cfv(ctcl, c1), cid), c3)))))\n-| wi(wfun(ccnv(ccnv(c1))), wi(wbr(c0, c1, c2), wal(s0, wi(wbr(c0, c1, cv(s0)), wbr(c2, cun(cfv(ctcl, c1), cid), cv(s0))))))\n-| wi(wi(wfun(ccnv(ccnv(c1))), wi(wbr(c0, c1, c2), wal(s0, wi(wbr(c0, c1, cv(s0)), wbr(c2, cun(cfv(ctcl, c1), cid), cv(s0)))))), wi(wi(wal(s0, wi(wbr(c0, c1, cv(s0)), wbr(c2, cun(cfv(ctcl, c1), cid), cv(s0)))), wi(wbr(c0, cfv(ctcl, c1), c3), wbr(c2, cun(cfv(ctcl, c1), cid), c3))), wi(wfun(ccnv(ccnv(c1))), wi(wbr(c0, c1, c2), wi(wbr(c0, cfv(ctcl, c1), c3), wbr(c2, cun(cfv(ctcl, c1), cid), c3))))))","pretty":"⊢ ((∀(s0,(c0[c1]s0 → c2[((t+ ` c1)⋃ =)]s0))→(c0[(t+ ` c1)]c3 → c2[((t+ ` c1)⋃ =)]c3))→(Fun(`' `' c1)→(c0[c1]c2 →(c0[(t+ ` c1)]c3 → c2[((t+ ` c1)⋃ =)]c3))))\n⊣ (Fun(`' `' c1)→(c0[c1]c2 → ∀(s0,(c0[c1]s0 → c2[((t+ ` c1)⋃ =)]s0))))\n⊣ ((Fun(`' `' c1)→(c0[c1]c2 → ∀(s0,(c0[c1]s0 → c2[((t+ ` c1)⋃ =)]s0))))→((∀(s0,(c0[c1]s0 → c2[((t+ ` c1)⋃ =)]s0))→(c0[(t+ ` c1)]c3 → c2[((t+ ` c1)⋃ =)]c3))→(Fun(`' `' c1)→(c0[c1]c2 →(c0[(t+ ` c1)]c3 → c2[((t+ ` c1)⋃ =)]c3)))))"}},{"stmt":{"origin":"alrimdv(s0, wfun(ccnv(ccnv(c1))), wbr(c0, c1, c2), wi(wbr(c0, c1, cv(s0)), wbr(c2, cun(cfv(ctcl, c1), cid), cv(s0))))","pretty":"alrimdv(s0, Fun(`' `' c1), c0[c1]c2, (c0[c1]s0 → c2[((t+ ` c1)⋃ =)]s0))"},"body":{"origin":"|- wi(wfun(ccnv(ccnv(c1))), wi(wbr(c0, c1, c2), wal(s0, wi(wbr(c0, c1, cv(s0)), wbr(c2, cun(cfv(ctcl, c1), cid), cv(s0))))))\n-| wi(wfun(ccnv(ccnv(c1))), wi(wbr(c0, c1, c2), wi(wbr(c0, c1, cv(s0)), wbr(c2, cun(cfv(ctcl, c1), cid), cv(s0)))))\n-| diffsw(s0, wfun(ccnv(ccnv(c1))))\n-| diffsw(s0, wbr(c0, c1, c2))","pretty":"⊢ (Fun(`' `' c1)→(c0[c1]c2 → ∀(s0,(c0[c1]s0 → c2[((t+ ` c1)⋃ =)]s0))))\n⊣ (Fun(`' `' c1)→(c0[c1]c2 →(c0[c1]s0 → c2[((t+ ` c1)⋃ =)]s0)))\n⊣ d(s0, Fun(`' `' c1))\n⊣ d(s0, c0[c1]c2)"},"cumulated":{"origin":"|- wi(wi(wal(s0, wi(wbr(c0, c1, cv(s0)), wbr(c2, cun(cfv(ctcl, c1), cid), cv(s0)))), wi(wbr(c0, cfv(ctcl, c1), c3), wbr(c2, cun(cfv(ctcl, c1), cid), c3))), wi(wfun(ccnv(ccnv(c1))), wi(wbr(c0, c1, c2), wi(wbr(c0, cfv(ctcl, c1), c3), wbr(c2, cun(cfv(ctcl, c1), cid), c3)))))\n-| wi(wi(wfun(ccnv(ccnv(c1))), wi(wbr(c0, c1, c2), wal(s0, wi(wbr(c0, c1, cv(s0)), wbr(c2, cun(cfv(ctcl, c1), cid), cv(s0)))))), wi(wi(wal(s0, wi(wbr(c0, c1, cv(s0)), wbr(c2, cun(cfv(ctcl, c1), cid), cv(s0)))), wi(wbr(c0, cfv(ctcl, c1), c3), wbr(c2, cun(cfv(ctcl, c1), cid), c3))), wi(wfun(ccnv(ccnv(c1))), wi(wbr(c0, c1, c2), wi(wbr(c0, cfv(ctcl, c1), c3), wbr(c2, cun(cfv(ctcl, c1), cid), c3))))))\n-| wi(wfun(ccnv(ccnv(c1))), wi(wbr(c0, c1, c2), wi(wbr(c0, c1, cv(s0)), wbr(c2, cun(cfv(ctcl, c1), cid), cv(s0)))))\n-| diffsw(s0, wfun(ccnv(ccnv(c1))))\n-| diffsw(s0, wbr(c0, c1, c2))","pretty":"⊢ ((∀(s0,(c0[c1]s0 → c2[((t+ ` c1)⋃ =)]s0))→(c0[(t+ ` c1)]c3 → c2[((t+ ` c1)⋃ =)]c3))→(Fun(`' `' c1)→(c0[c1]c2 →(c0[(t+ ` c1)]c3 → c2[((t+ ` c1)⋃ =)]c3))))\n⊣ ((Fun(`' `' c1)→(c0[c1]c2 → ∀(s0,(c0[c1]s0 → c2[((t+ ` c1)⋃ =)]s0))))→((∀(s0,(c0[c1]s0 → c2[((t+ ` c1)⋃ =)]s0))→(c0[(t+ ` c1)]c3 → c2[((t+ ` c1)⋃ =)]c3))→(Fun(`' `' c1)→(c0[c1]c2 →(c0[(t+ ` c1)]c3 → c2[((t+ ` c1)⋃ =)]c3)))))\n⊣ (Fun(`' `' c1)→(c0[c1]c2 →(c0[c1]s0 → c2[((t+ ` c1)⋃ =)]s0)))\n⊣ d(s0, Fun(`' `' c1))\n⊣ d(s0, c0[c1]c2)"}},{"stmt":{"origin":"frege122(c1, c0, c2, cv(s0), c4, c5, universe)","pretty":"frege122(c1, c0, c2, s0, c4, c5, universe)"},"body":{"origin":"|- wi(wfun(ccnv(ccnv(c1))), wi(wbr(c0, c1, c2), wi(wbr(c0, c1, cv(s0)), wbr(c2, cun(cfv(ctcl, c1), cid), cv(s0)))))\n-| wcel(c2, c4)\n-| wcel(c0, c5)\n-| wcel(cv(s0), universe)","pretty":"⊢ (Fun(`' `' c1)→(c0[c1]c2 →(c0[c1]s0 → c2[((t+ ` c1)⋃ =)]s0)))\n⊣ c2 ∈ c4\n⊣ c0 ∈ c5\n⊣ s0 ∈ 𝕌"},"cumulated":{"origin":"|- wi(wi(wal(s0, wi(wbr(c0, c1, cv(s0)), wbr(c2, cun(cfv(ctcl, c1), cid), cv(s0)))), wi(wbr(c0, cfv(ctcl, c1), c3), wbr(c2, cun(cfv(ctcl, c1), cid), c3))), wi(wfun(ccnv(ccnv(c1))), wi(wbr(c0, c1, c2), wi(wbr(c0, cfv(ctcl, c1), c3), wbr(c2, cun(cfv(ctcl, c1), cid), c3)))))\n-| wi(wi(wfun(ccnv(ccnv(c1))), wi(wbr(c0, c1, c2), wal(s0, wi(wbr(c0, c1, cv(s0)), wbr(c2, cun(cfv(ctcl, c1), cid), cv(s0)))))), wi(wi(wal(s0, wi(wbr(c0, c1, cv(s0)), wbr(c2, cun(cfv(ctcl, c1), cid), cv(s0)))), wi(wbr(c0, cfv(ctcl, c1), c3), wbr(c2, cun(cfv(ctcl, c1), cid), c3))), wi(wfun(ccnv(ccnv(c1))), wi(wbr(c0, c1, c2), wi(wbr(c0, cfv(ctcl, c1), c3), wbr(c2, cun(cfv(ctcl, c1), cid), c3))))))\n-| diffsw(s0, wfun(ccnv(ccnv(c1))))\n-| diffsw(s0, wbr(c0, c1, c2))\n-| wcel(c2, c4)\n-| wcel(c0, c5)\n-| wcel(cv(s0), universe)","pretty":"⊢ ((∀(s0,(c0[c1]s0 → c2[((t+ ` c1)⋃ =)]s0))→(c0[(t+ ` c1)]c3 → c2[((t+ ` c1)⋃ =)]c3))→(Fun(`' `' c1)→(c0[c1]c2 →(c0[(t+ ` c1)]c3 → c2[((t+ ` c1)⋃ =)]c3))))\n⊣ ((Fun(`' `' c1)→(c0[c1]c2 → ∀(s0,(c0[c1]s0 → c2[((t+ ` c1)⋃ =)]s0))))→((∀(s0,(c0[c1]s0 → c2[((t+ ` c1)⋃ =)]s0))→(c0[(t+ ` c1)]c3 → c2[((t+ ` c1)⋃ =)]c3))→(Fun(`' `' c1)→(c0[c1]c2 →(c0[(t+ ` c1)]c3 → c2[((t+ ` c1)⋃ =)]c3)))))\n⊣ d(s0, Fun(`' `' c1))\n⊣ d(s0, c0[c1]c2)\n⊣ c2 ∈ c4\n⊣ c0 ∈ c5\n⊣ s0 ∈ 𝕌"}},{"stmt":{"origin":"vex(s0)","pretty":"vex(s0)"},"body":{"origin":"|- wcel(cv(s0), universe)","pretty":"⊢ s0 ∈ 𝕌"},"cumulated":{"origin":"|- wi(wi(wal(s0, wi(wbr(c0, c1, cv(s0)), wbr(c2, cun(cfv(ctcl, c1), cid), cv(s0)))), wi(wbr(c0, cfv(ctcl, c1), c3), wbr(c2, cun(cfv(ctcl, c1), cid), c3))), wi(wfun(ccnv(ccnv(c1))), wi(wbr(c0, c1, c2), wi(wbr(c0, cfv(ctcl, c1), c3), wbr(c2, cun(cfv(ctcl, c1), cid), c3)))))\n-| wi(wi(wfun(ccnv(ccnv(c1))), wi(wbr(c0, c1, c2), wal(s0, wi(wbr(c0, c1, cv(s0)), wbr(c2, cun(cfv(ctcl, c1), cid), cv(s0)))))), wi(wi(wal(s0, wi(wbr(c0, c1, cv(s0)), wbr(c2, cun(cfv(ctcl, c1), cid), cv(s0)))), wi(wbr(c0, cfv(ctcl, c1), c3), wbr(c2, cun(cfv(ctcl, c1), cid), c3))), wi(wfun(ccnv(ccnv(c1))), wi(wbr(c0, c1, c2), wi(wbr(c0, cfv(ctcl, c1), c3), wbr(c2, cun(cfv(ctcl, c1), cid), c3))))))\n-| diffsw(s0, wfun(ccnv(ccnv(c1))))\n-| diffsw(s0, wbr(c0, c1, c2))\n-| wcel(c2, c4)\n-| wcel(c0, c5)","pretty":"⊢ ((∀(s0,(c0[c1]s0 → c2[((t+ ` c1)⋃ =)]s0))→(c0[(t+ ` c1)]c3 → c2[((t+ ` c1)⋃ =)]c3))→(Fun(`' `' c1)→(c0[c1]c2 →(c0[(t+ ` c1)]c3 → c2[((t+ ` c1)⋃ =)]c3))))\n⊣ ((Fun(`' `' c1)→(c0[c1]c2 → ∀(s0,(c0[c1]s0 → c2[((t+ ` c1)⋃ =)]s0))))→((∀(s0,(c0[c1]s0 → c2[((t+ ` c1)⋃ =)]s0))→(c0[(t+ ` c1)]c3 → c2[((t+ ` c1)⋃ =)]c3))→(Fun(`' `' c1)→(c0[c1]c2 →(c0[(t+ ` c1)]c3 → c2[((t+ ` c1)⋃ =)]c3)))))\n⊣ d(s0, Fun(`' `' c1))\n⊣ d(s0, c0[c1]c2)\n⊣ c2 ∈ c4\n⊣ c0 ∈ c5"}},{"stmt":{"origin":"frege19(wfun(ccnv(ccnv(c1))), wbr(c0, c1, c2), wal(s0, wi(wbr(c0, c1, cv(s0)), wbr(c2, cun(cfv(ctcl, c1), cid), cv(s0)))), wi(wbr(c0, cfv(ctcl, c1), c3), wbr(c2, cun(cfv(ctcl, c1), cid), c3)))","pretty":"frege19(Fun(`' `' c1), c0[c1]c2, ∀(s0,(c0[c1]s0 → c2[((t+ ` c1)⋃ =)]s0)), (c0[(t+ ` c1)]c3 → c2[((t+ ` c1)⋃ =)]c3))"},"body":{"origin":"|- wi(wi(wfun(ccnv(ccnv(c1))), wi(wbr(c0, c1, c2), wal(s0, wi(wbr(c0, c1, cv(s0)), wbr(c2, cun(cfv(ctcl, c1), cid), cv(s0)))))), wi(wi(wal(s0, wi(wbr(c0, c1, cv(s0)), wbr(c2, cun(cfv(ctcl, c1), cid), cv(s0)))), wi(wbr(c0, cfv(ctcl, c1), c3), wbr(c2, cun(cfv(ctcl, c1), cid), c3))), wi(wfun(ccnv(ccnv(c1))), wi(wbr(c0, c1, c2), wi(wbr(c0, cfv(ctcl, c1), c3), wbr(c2, cun(cfv(ctcl, c1), cid), c3))))))","pretty":"⊢ ((Fun(`' `' c1)→(c0[c1]c2 → ∀(s0,(c0[c1]s0 → c2[((t+ ` c1)⋃ =)]s0))))→((∀(s0,(c0[c1]s0 → c2[((t+ ` c1)⋃ =)]s0))→(c0[(t+ ` c1)]c3 → c2[((t+ ` c1)⋃ =)]c3))→(Fun(`' `' c1)→(c0[c1]c2 →(c0[(t+ ` c1)]c3 → c2[((t+ ` c1)⋃ =)]c3)))))"},"cumulated":{"origin":"|- wi(wi(wal(s0, wi(wbr(c0, c1, cv(s0)), wbr(c2, cun(cfv(ctcl, c1), cid), cv(s0)))), wi(wbr(c0, cfv(ctcl, c1), c3), wbr(c2, cun(cfv(ctcl, c1), cid), c3))), wi(wfun(ccnv(ccnv(c1))), wi(wbr(c0, c1, c2), wi(wbr(c0, cfv(ctcl, c1), c3), wbr(c2, cun(cfv(ctcl, c1), cid), c3)))))\n-| diffsw(s0, wfun(ccnv(ccnv(c1))))\n-| diffsw(s0, wbr(c0, c1, c2))\n-| wcel(c2, c4)\n-| wcel(c0, c5)","pretty":"⊢ ((∀(s0,(c0[c1]s0 → c2[((t+ ` c1)⋃ =)]s0))→(c0[(t+ ` c1)]c3 → c2[((t+ ` c1)⋃ =)]c3))→(Fun(`' `' c1)→(c0[c1]c2 →(c0[(t+ ` c1)]c3 → c2[((t+ ` c1)⋃ =)]c3))))\n⊣ d(s0, Fun(`' `' c1))\n⊣ d(s0, c0[c1]c2)\n⊣ c2 ∈ c4\n⊣ c0 ∈ c5"}},{"stmt":{"origin":"diff.wfun.s(s0, ccnv(ccnv(c1)))","pretty":"diff.wfun.s(s0, `' `' c1)"},"body":{"origin":"|- diffsw(s0, wfun(ccnv(ccnv(c1))))\n-| diffsc(s0, ccnv(ccnv(c1)))","pretty":"⊢ d(s0, Fun(`' `' c1))\n⊣ d(s0, `' `' c1)"},"cumulated":{"origin":"|- wi(wi(wal(s0, wi(wbr(c0, c1, cv(s0)), wbr(c2, cun(cfv(ctcl, c1), cid), cv(s0)))), wi(wbr(c0, cfv(ctcl, c1), c3), wbr(c2, cun(cfv(ctcl, c1), cid), c3))), wi(wfun(ccnv(ccnv(c1))), wi(wbr(c0, c1, c2), wi(wbr(c0, cfv(ctcl, c1), c3), wbr(c2, cun(cfv(ctcl, c1), cid), c3)))))\n-| diffsw(s0, wbr(c0, c1, c2))\n-| wcel(c2, c4)\n-| wcel(c0, c5)\n-| diffsc(s0, ccnv(ccnv(c1)))","pretty":"⊢ ((∀(s0,(c0[c1]s0 → c2[((t+ ` c1)⋃ =)]s0))→(c0[(t+ ` c1)]c3 → c2[((t+ ` c1)⋃ =)]c3))→(Fun(`' `' c1)→(c0[c1]c2 →(c0[(t+ ` c1)]c3 → c2[((t+ ` c1)⋃ =)]c3))))\n⊣ d(s0, c0[c1]c2)\n⊣ c2 ∈ c4\n⊣ c0 ∈ c5\n⊣ d(s0, `' `' c1)"}},{"stmt":{"origin":"diff.ccnv.s(s0, ccnv(c1))","pretty":"diff.ccnv.s(s0, `' c1)"},"body":{"origin":"|- diffsc(s0, ccnv(ccnv(c1)))\n-| diffsc(s0, ccnv(c1))","pretty":"⊢ d(s0, `' `' c1)\n⊣ d(s0, `' c1)"},"cumulated":{"origin":"|- wi(wi(wal(s0, wi(wbr(c0, c1, cv(s0)), wbr(c2, cun(cfv(ctcl, c1), cid), cv(s0)))), wi(wbr(c0, cfv(ctcl, c1), c3), wbr(c2, cun(cfv(ctcl, c1), cid), c3))), wi(wfun(ccnv(ccnv(c1))), wi(wbr(c0, c1, c2), wi(wbr(c0, cfv(ctcl, c1), c3), wbr(c2, cun(cfv(ctcl, c1), cid), c3)))))\n-| diffsw(s0, wbr(c0, c1, c2))\n-| wcel(c2, c4)\n-| wcel(c0, c5)\n-| diffsc(s0, ccnv(c1))","pretty":"⊢ ((∀(s0,(c0[c1]s0 → c2[((t+ ` c1)⋃ =)]s0))→(c0[(t+ ` c1)]c3 → c2[((t+ ` c1)⋃ =)]c3))→(Fun(`' `' c1)→(c0[c1]c2 →(c0[(t+ ` c1)]c3 → c2[((t+ ` c1)⋃ =)]c3))))\n⊣ d(s0, c0[c1]c2)\n⊣ c2 ∈ c4\n⊣ c0 ∈ c5\n⊣ d(s0, `' c1)"}},{"stmt":{"origin":"diff.ccnv.s(s0, c1)","pretty":"diff.ccnv.s(s0, c1)"},"body":{"origin":"|- diffsc(s0, ccnv(c1))\n-| diffsc(s0, c1)","pretty":"⊢ d(s0, `' c1)\n⊣ d(s0, c1)"},"cumulated":{"origin":"|- wi(wi(wal(s0, wi(wbr(c0, c1, cv(s0)), wbr(c2, cun(cfv(ctcl, c1), cid), cv(s0)))), wi(wbr(c0, cfv(ctcl, c1), c3), wbr(c2, cun(cfv(ctcl, c1), cid), c3))), wi(wfun(ccnv(ccnv(c1))), wi(wbr(c0, c1, c2), wi(wbr(c0, cfv(ctcl, c1), c3), wbr(c2, cun(cfv(ctcl, c1), cid), c3)))))\n-| diffsw(s0, wbr(c0, c1, c2))\n-| wcel(c2, c4)\n-| wcel(c0, c5)\n-| diffsc(s0, c1)","pretty":"⊢ ((∀(s0,(c0[c1]s0 → c2[((t+ ` c1)⋃ =)]s0))→(c0[(t+ ` c1)]c3 → c2[((t+ ` c1)⋃ =)]c3))→(Fun(`' `' c1)→(c0[c1]c2 →(c0[(t+ ` c1)]c3 → c2[((t+ ` c1)⋃ =)]c3))))\n⊣ d(s0, c0[c1]c2)\n⊣ c2 ∈ c4\n⊣ c0 ∈ c5\n⊣ d(s0, c1)"}},{"stmt":{"origin":"diff.wbr.s(s0, c0, c1, c2)","pretty":"diff.wbr.s(s0, c0, c1, c2)"},"body":{"origin":"|- diffsw(s0, wbr(c0, c1, c2))\n-| diffsc(s0, c0)\n-| diffsc(s0, c1)\n-| diffsc(s0, c2)","pretty":"⊢ d(s0, c0[c1]c2)\n⊣ d(s0, c0)\n⊣ d(s0, c1)\n⊣ d(s0, c2)"},"cumulated":{"origin":"|- wi(wi(wal(s0, wi(wbr(c0, c1, cv(s0)), wbr(c2, cun(cfv(ctcl, c1), cid), cv(s0)))), wi(wbr(c0, cfv(ctcl, c1), c3), wbr(c2, cun(cfv(ctcl, c1), cid), c3))), wi(wfun(ccnv(ccnv(c1))), wi(wbr(c0, c1, c2), wi(wbr(c0, cfv(ctcl, c1), c3), wbr(c2, cun(cfv(ctcl, c1), cid), c3)))))\n-| wcel(c2, c4)\n-| wcel(c0, c5)\n-| diffsc(s0, c1)\n-| diffsc(s0, c0)\n-| diffsc(s0, c2)","pretty":"⊢ ((∀(s0,(c0[c1]s0 → c2[((t+ ` c1)⋃ =)]s0))→(c0[(t+ ` c1)]c3 → c2[((t+ ` c1)⋃ =)]c3))→(Fun(`' `' c1)→(c0[c1]c2 →(c0[(t+ ` c1)]c3 → c2[((t+ ` c1)⋃ =)]c3))))\n⊣ c2 ∈ c4\n⊣ c0 ∈ c5\n⊣ d(s0, c1)\n⊣ d(s0, c0)\n⊣ d(s0, c2)"}}],"comment":"Lemma for ~ frege124 . Proposition 123 of [Frege1879] p. 79. (Contributed by RP, 8-Jul-2020.) (Proof modification is discouraged.)","parent":["ax-mp","alrimdv","frege122","vex","frege19","diff.wfun.s","diff.ccnv.s","diff.wbr.s"],"children":["frege124"]}