{"bIdx":25310,"bType":"thm","type":"","name":"iimulcn","params":"setvar s0, setvar s1","body":["|- wcel(cmpo(s0, s1, co(nat0, cicc, nat1), co(nat0, cicc, nat1), co(cv(s0), cmul, cv(s1))), co(co(cii, ctx, cii), ccn, cii))","-| diffss(s0, s1)"],"bodyPretty":["⊢ (s0 ∈(0[[,]]1), s1 ∈(0[[,]]1)↦(s0[×]s1))∈((II[tX]II)[Cn]II)","⊣ d(s0, s1)"],"proof":[{"stmt":{"origin":"eleqtrri(cmpo(s0, s1, co(nat0, cicc, nat1), co(nat0, cicc, nat1), co(cv(s0), cmul, cv(s1))), co(co(cii, ctx, cii), ccn, cii), co(co(cii, ctx, cii), ccn, co(cfv(ctopn, ccnfld), crest, co(nat0, cicc, nat1))))","pretty":"eleqtrri((s0 ∈(0[[,]]1), s1 ∈(0[[,]]1)↦(s0[×]s1)), ((II[tX]II)[Cn]II), ((II[tX]II)[Cn]((TopOpen ` CCfld)[|`t](0[[,]]1))))"},"body":{"origin":"|- wcel(cmpo(s0, s1, co(nat0, cicc, nat1), co(nat0, cicc, nat1), co(cv(s0), cmul, cv(s1))), co(co(cii, ctx, cii), ccn, cii))\n-| wcel(cmpo(s0, s1, co(nat0, cicc, nat1), co(nat0, cicc, nat1), co(cv(s0), cmul, cv(s1))), co(co(cii, ctx, cii), ccn, co(cfv(ctopn, ccnfld), crest, co(nat0, cicc, nat1))))\n-| wceq(co(co(cii, ctx, cii), ccn, cii), co(co(cii, ctx, cii), ccn, co(cfv(ctopn, ccnfld), crest, co(nat0, cicc, nat1))))","pretty":"⊢ (s0 ∈(0[[,]]1), s1 ∈(0[[,]]1)↦(s0[×]s1))∈((II[tX]II)[Cn]II)\n⊣ (s0 ∈(0[[,]]1), s1 ∈(0[[,]]1)↦(s0[×]s1))∈((II[tX]II)[Cn]((TopOpen ` CCfld)[|`t](0[[,]]1)))\n⊣ ((II[tX]II)[Cn]II)=((II[tX]II)[Cn]((TopOpen ` CCfld)[|`t](0[[,]]1)))"},"cumulated":{"origin":"|- wcel(cmpo(s0, s1, co(nat0, cicc, nat1), co(nat0, cicc, nat1), co(cv(s0), cmul, cv(s1))), co(co(cii, ctx, cii), ccn, cii))\n-| wcel(cmpo(s0, s1, co(nat0, cicc, nat1), co(nat0, cicc, nat1), co(cv(s0), cmul, cv(s1))), co(co(cii, ctx, cii), ccn, co(cfv(ctopn, ccnfld), crest, co(nat0, cicc, nat1))))\n-| wceq(co(co(cii, ctx, cii), ccn, cii), co(co(cii, ctx, cii), ccn, co(cfv(ctopn, ccnfld), crest, co(nat0, cicc, nat1))))","pretty":"⊢ (s0 ∈(0[[,]]1), s1 ∈(0[[,]]1)↦(s0[×]s1))∈((II[tX]II)[Cn]II)\n⊣ (s0 ∈(0[[,]]1), s1 ∈(0[[,]]1)↦(s0[×]s1))∈((II[tX]II)[Cn]((TopOpen ` CCfld)[|`t](0[[,]]1)))\n⊣ ((II[tX]II)[Cn]II)=((II[tX]II)[Cn]((TopOpen ` CCfld)[|`t](0[[,]]1)))"}},{"stmt":{"origin":"mpbi(wcel(cmpo(s0, s1, co(nat0, cicc, nat1), co(nat0, cicc, nat1), co(cv(s0), cmul, cv(s1))), co(co(cii, ctx, cii), ccn, co(cfv(ctopn, ccnfld), crest, co(nat0, cicc, nat1)))), wcel(cmpo(s0, s1, co(nat0, cicc, nat1), co(nat0, cicc, nat1), co(cv(s0), cmul, cv(s1))), co(co(cii, ctx, cii), ccn, cfv(ctopn, ccnfld))))","pretty":"mpbi((s0 ∈(0[[,]]1), s1 ∈(0[[,]]1)↦(s0[×]s1))∈((II[tX]II)[Cn]((TopOpen ` CCfld)[|`t](0[[,]]1))), (s0 ∈(0[[,]]1), s1 ∈(0[[,]]1)↦(s0[×]s1))∈((II[tX]II)[Cn](TopOpen ` CCfld)))"},"body":{"origin":"|- wcel(cmpo(s0, s1, co(nat0, cicc, nat1), co(nat0, cicc, nat1), co(cv(s0), cmul, cv(s1))), co(co(cii, ctx, cii), ccn, co(cfv(ctopn, ccnfld), crest, co(nat0, cicc, nat1))))\n-| wcel(cmpo(s0, s1, co(nat0, cicc, nat1), co(nat0, cicc, nat1), co(cv(s0), cmul, cv(s1))), co(co(cii, ctx, cii), ccn, cfv(ctopn, ccnfld)))\n-| wb(wcel(cmpo(s0, s1, co(nat0, cicc, nat1), co(nat0, cicc, nat1), co(cv(s0), cmul, cv(s1))), co(co(cii, ctx, cii), ccn, cfv(ctopn, ccnfld))), wcel(cmpo(s0, s1, co(nat0, cicc, nat1), co(nat0, cicc, nat1), co(cv(s0), cmul, cv(s1))), co(co(cii, ctx, cii), ccn, co(cfv(ctopn, ccnfld), crest, co(nat0, cicc, nat1)))))","pretty":"⊢ (s0 ∈(0[[,]]1), s1 ∈(0[[,]]1)↦(s0[×]s1))∈((II[tX]II)[Cn]((TopOpen ` CCfld)[|`t](0[[,]]1)))\n⊣ (s0 ∈(0[[,]]1), s1 ∈(0[[,]]1)↦(s0[×]s1))∈((II[tX]II)[Cn](TopOpen ` CCfld))\n⊣ ((s0 ∈(0[[,]]1), s1 ∈(0[[,]]1)↦(s0[×]s1))∈((II[tX]II)[Cn](TopOpen ` CCfld))↔(s0 ∈(0[[,]]1), s1 ∈(0[[,]]1)↦(s0[×]s1))∈((II[tX]II)[Cn]((TopOpen ` CCfld)[|`t](0[[,]]1))))"},"cumulated":{"origin":"|- wcel(cmpo(s0, s1, co(nat0, cicc, nat1), co(nat0, cicc, nat1), co(cv(s0), cmul, cv(s1))), co(co(cii, ctx, cii), ccn, cii))\n-| wceq(co(co(cii, ctx, cii), ccn, cii), co(co(cii, ctx, cii), ccn, co(cfv(ctopn, ccnfld), crest, co(nat0, cicc, nat1))))\n-| wcel(cmpo(s0, s1, co(nat0, cicc, nat1), co(nat0, cicc, nat1), co(cv(s0), cmul, cv(s1))), co(co(cii, ctx, cii), ccn, cfv(ctopn, ccnfld)))\n-| wb(wcel(cmpo(s0, s1, co(nat0, cicc, nat1), co(nat0, cicc, nat1), co(cv(s0), cmul, cv(s1))), co(co(cii, ctx, cii), ccn, cfv(ctopn, ccnfld))), wcel(cmpo(s0, s1, co(nat0, cicc, nat1), co(nat0, cicc, nat1), co(cv(s0), cmul, cv(s1))), co(co(cii, ctx, cii), ccn, co(cfv(ctopn, ccnfld), crest, co(nat0, cicc, nat1)))))","pretty":"⊢ (s0 ∈(0[[,]]1), s1 ∈(0[[,]]1)↦(s0[×]s1))∈((II[tX]II)[Cn]II)\n⊣ ((II[tX]II)[Cn]II)=((II[tX]II)[Cn]((TopOpen ` CCfld)[|`t](0[[,]]1)))\n⊣ (s0 ∈(0[[,]]1), s1 ∈(0[[,]]1)↦(s0[×]s1))∈((II[tX]II)[Cn](TopOpen ` CCfld))\n⊣ ((s0 ∈(0[[,]]1), s1 ∈(0[[,]]1)↦(s0[×]s1))∈((II[tX]II)[Cn](TopOpen ` CCfld))↔(s0 ∈(0[[,]]1), s1 ∈(0[[,]]1)↦(s0[×]s1))∈((II[tX]II)[Cn]((TopOpen ` CCfld)[|`t](0[[,]]1))))"}},{"stmt":{"origin":"mptru(wcel(cmpo(s0, s1, co(nat0, cicc, nat1), co(nat0, cicc, nat1), co(cv(s0), cmul, cv(s1))), co(co(cii, ctx, cii), ccn, cfv(ctopn, ccnfld))))","pretty":"mptru((s0 ∈(0[[,]]1), s1 ∈(0[[,]]1)↦(s0[×]s1))∈((II[tX]II)[Cn](TopOpen ` CCfld)))"},"body":{"origin":"|- wcel(cmpo(s0, s1, co(nat0, cicc, nat1), co(nat0, cicc, nat1), co(cv(s0), cmul, cv(s1))), co(co(cii, ctx, cii), ccn, cfv(ctopn, ccnfld)))\n-| wi(wtru, wcel(cmpo(s0, s1, co(nat0, cicc, nat1), co(nat0, cicc, nat1), co(cv(s0), cmul, cv(s1))), co(co(cii, ctx, cii), ccn, cfv(ctopn, ccnfld))))","pretty":"⊢ (s0 ∈(0[[,]]1), s1 ∈(0[[,]]1)↦(s0[×]s1))∈((II[tX]II)[Cn](TopOpen ` CCfld))\n⊣ (T →(s0 ∈(0[[,]]1), s1 ∈(0[[,]]1)↦(s0[×]s1))∈((II[tX]II)[Cn](TopOpen ` CCfld)))"},"cumulated":{"origin":"|- wcel(cmpo(s0, s1, co(nat0, cicc, nat1), co(nat0, cicc, nat1), co(cv(s0), cmul, cv(s1))), co(co(cii, ctx, cii), ccn, cii))\n-| wceq(co(co(cii, ctx, cii), ccn, cii), co(co(cii, ctx, cii), ccn, co(cfv(ctopn, ccnfld), crest, co(nat0, cicc, nat1))))\n-| wb(wcel(cmpo(s0, s1, co(nat0, cicc, nat1), co(nat0, cicc, nat1), co(cv(s0), cmul, cv(s1))), co(co(cii, ctx, cii), ccn, cfv(ctopn, ccnfld))), wcel(cmpo(s0, s1, co(nat0, cicc, nat1), co(nat0, cicc, nat1), co(cv(s0), cmul, cv(s1))), co(co(cii, ctx, cii), ccn, co(cfv(ctopn, ccnfld), crest, co(nat0, cicc, nat1)))))\n-| wi(wtru, wcel(cmpo(s0, s1, co(nat0, cicc, nat1), co(nat0, cicc, nat1), co(cv(s0), cmul, cv(s1))), co(co(cii, ctx, cii), ccn, cfv(ctopn, ccnfld))))","pretty":"⊢ (s0 ∈(0[[,]]1), s1 ∈(0[[,]]1)↦(s0[×]s1))∈((II[tX]II)[Cn]II)\n⊣ ((II[tX]II)[Cn]II)=((II[tX]II)[Cn]((TopOpen ` CCfld)[|`t](0[[,]]1)))\n⊣ ((s0 ∈(0[[,]]1), s1 ∈(0[[,]]1)↦(s0[×]s1))∈((II[tX]II)[Cn](TopOpen ` CCfld))↔(s0 ∈(0[[,]]1), s1 ∈(0[[,]]1)↦(s0[×]s1))∈((II[tX]II)[Cn]((TopOpen ` CCfld)[|`t](0[[,]]1))))\n⊣ (T →(s0 ∈(0[[,]]1), s1 ∈(0[[,]]1)↦(s0[×]s1))∈((II[tX]II)[Cn](TopOpen ` CCfld)))"}},{"stmt":{"origin":"cnmpt2res(s0, s1, co(nat0, cicc, nat1), co(nat0, cicc, nat1), co(cv(s0), cmul, cv(s1)), cii, cii, cfv(ctopn, ccnfld), cfv(ctopn, ccnfld), cc, cfv(ctopn, ccnfld), cc, wtru)","pretty":"cnmpt2res(s0, s1, (0[[,]]1), (0[[,]]1), (s0[×]s1), cii, cii, (TopOpen ` CCfld), (TopOpen ` CCfld), cc, (TopOpen ` CCfld), cc, wtru)"},"body":{"origin":"|- wi(wtru, wcel(cmpo(s0, s1, co(nat0, cicc, nat1), co(nat0, cicc, nat1), co(cv(s0), cmul, cv(s1))), co(co(cii, ctx, cii), ccn, cfv(ctopn, ccnfld))))\n-| wceq(cii, co(cfv(ctopn, ccnfld), crest, co(nat0, cicc, nat1)))\n-| wi(wtru, wcel(cfv(ctopn, ccnfld), cfv(ctopon, cc)))\n-| wi(wtru, wss(co(nat0, cicc, nat1), cc))\n-| wceq(cii, co(cfv(ctopn, ccnfld), crest, co(nat0, cicc, nat1)))\n-| wi(wtru, wcel(cfv(ctopn, ccnfld), cfv(ctopon, cc)))\n-| wi(wtru, wss(co(nat0, cicc, nat1), cc))\n-| wi(wtru, wcel(cmpo(s0, s1, cc, cc, co(cv(s0), cmul, cv(s1))), co(co(cfv(ctopn, ccnfld), ctx, cfv(ctopn, ccnfld)), ccn, cfv(ctopn, ccnfld))))\n-| diffss(s0, s1)\n-| diffsc(s0, co(nat0, cicc, nat1))\n-| diffsc(s0, co(nat0, cicc, nat1))\n-| diffsc(s0, cc)\n-| diffsc(s0, cc)\n-| diffsc(s1, co(nat0, cicc, nat1))\n-| diffsc(s1, co(nat0, cicc, nat1))\n-| diffsc(s1, cc)\n-| diffsc(s1, cc)","pretty":"⊢ (T →(s0 ∈(0[[,]]1), s1 ∈(0[[,]]1)↦(s0[×]s1))∈((II[tX]II)[Cn](TopOpen ` CCfld)))\n⊣ II =((TopOpen ` CCfld)[|`t](0[[,]]1))\n⊣ (T →(TopOpen ` CCfld)∈(TopOn ` ℂ))\n⊣ (T →(0[[,]]1)⊆ ℂ)\n⊣ II =((TopOpen ` CCfld)[|`t](0[[,]]1))\n⊣ (T →(TopOpen ` CCfld)∈(TopOn ` ℂ))\n⊣ (T →(0[[,]]1)⊆ ℂ)\n⊣ (T →(s0 ∈ ℂ, s1 ∈ ℂ ↦(s0[×]s1))∈(((TopOpen ` CCfld)[tX](TopOpen ` CCfld))[Cn](TopOpen ` CCfld)))\n⊣ d(s0, s1)\n⊣ d(s0,(0[[,]]1))\n⊣ d(s0,(0[[,]]1))\n⊣ d(s0, ℂ)\n⊣ d(s0, ℂ)\n⊣ d(s1,(0[[,]]1))\n⊣ d(s1,(0[[,]]1))\n⊣ d(s1, ℂ)\n⊣ d(s1, ℂ)"},"cumulated":{"origin":"|- wcel(cmpo(s0, s1, co(nat0, cicc, nat1), co(nat0, cicc, nat1), co(cv(s0), cmul, cv(s1))), co(co(cii, ctx, cii), ccn, cii))\n-| wceq(co(co(cii, ctx, cii), ccn, cii), co(co(cii, ctx, cii), ccn, co(cfv(ctopn, ccnfld), crest, co(nat0, cicc, nat1))))\n-| wb(wcel(cmpo(s0, s1, co(nat0, cicc, nat1), co(nat0, cicc, nat1), co(cv(s0), cmul, cv(s1))), co(co(cii, ctx, cii), ccn, cfv(ctopn, ccnfld))), wcel(cmpo(s0, s1, co(nat0, cicc, nat1), co(nat0, cicc, nat1), co(cv(s0), cmul, cv(s1))), co(co(cii, ctx, cii), ccn, co(cfv(ctopn, ccnfld), crest, co(nat0, cicc, nat1)))))\n-| wceq(cii, co(cfv(ctopn, ccnfld), crest, co(nat0, cicc, nat1)))\n-| wi(wtru, wcel(cfv(ctopn, ccnfld), cfv(ctopon, cc)))\n-| wi(wtru, wss(co(nat0, cicc, nat1), cc))\n-| wi(wtru, wcel(cmpo(s0, s1, cc, cc, co(cv(s0), cmul, cv(s1))), co(co(cfv(ctopn, ccnfld), ctx, cfv(ctopn, ccnfld)), ccn, cfv(ctopn, ccnfld))))\n-| diffss(s0, s1)\n-| diffsc(s0, co(nat0, cicc, nat1))\n-| diffsc(s0, cc)\n-| diffsc(s1, co(nat0, cicc, nat1))\n-| diffsc(s1, cc)","pretty":"⊢ (s0 ∈(0[[,]]1), s1 ∈(0[[,]]1)↦(s0[×]s1))∈((II[tX]II)[Cn]II)\n⊣ ((II[tX]II)[Cn]II)=((II[tX]II)[Cn]((TopOpen ` CCfld)[|`t](0[[,]]1)))\n⊣ ((s0 ∈(0[[,]]1), s1 ∈(0[[,]]1)↦(s0[×]s1))∈((II[tX]II)[Cn](TopOpen ` CCfld))↔(s0 ∈(0[[,]]1), s1 ∈(0[[,]]1)↦(s0[×]s1))∈((II[tX]II)[Cn]((TopOpen ` CCfld)[|`t](0[[,]]1))))\n⊣ II =((TopOpen ` CCfld)[|`t](0[[,]]1))\n⊣ (T →(TopOpen ` CCfld)∈(TopOn ` ℂ))\n⊣ (T →(0[[,]]1)⊆ ℂ)\n⊣ (T →(s0 ∈ ℂ, s1 ∈ ℂ ↦(s0[×]s1))∈(((TopOpen ` CCfld)[tX](TopOpen ` CCfld))[Cn](TopOpen ` CCfld)))\n⊣ d(s0, s1)\n⊣ d(s0,(0[[,]]1))\n⊣ d(s0, ℂ)\n⊣ d(s1,(0[[,]]1))\n⊣ d(s1, ℂ)"}},{"stmt":{"origin":"a1i(wtru, wcel(cfv(ctopn, ccnfld), cfv(ctopon, cc)))","pretty":"a1i(wtru, (TopOpen ` CCfld)∈(TopOn ` ℂ))"},"body":{"origin":"|- wi(wtru, wcel(cfv(ctopn, ccnfld), cfv(ctopon, cc)))\n-| wcel(cfv(ctopn, ccnfld), cfv(ctopon, cc))","pretty":"⊢ (T →(TopOpen ` CCfld)∈(TopOn ` ℂ))\n⊣ (TopOpen ` CCfld)∈(TopOn ` ℂ)"},"cumulated":{"origin":"|- wcel(cmpo(s0, s1, co(nat0, cicc, nat1), co(nat0, cicc, nat1), co(cv(s0), cmul, cv(s1))), co(co(cii, ctx, cii), ccn, cii))\n-| wceq(co(co(cii, ctx, cii), ccn, cii), co(co(cii, ctx, cii), ccn, co(cfv(ctopn, ccnfld), crest, co(nat0, cicc, nat1))))\n-| wb(wcel(cmpo(s0, s1, co(nat0, cicc, nat1), co(nat0, cicc, nat1), co(cv(s0), cmul, cv(s1))), co(co(cii, ctx, cii), ccn, cfv(ctopn, ccnfld))), wcel(cmpo(s0, s1, co(nat0, cicc, nat1), co(nat0, cicc, nat1), co(cv(s0), cmul, cv(s1))), co(co(cii, ctx, cii), ccn, co(cfv(ctopn, ccnfld), crest, co(nat0, cicc, nat1)))))\n-| wceq(cii, co(cfv(ctopn, ccnfld), crest, co(nat0, cicc, nat1)))\n-| wi(wtru, wss(co(nat0, cicc, nat1), cc))\n-| wi(wtru, wcel(cmpo(s0, s1, cc, cc, co(cv(s0), cmul, cv(s1))), co(co(cfv(ctopn, ccnfld), ctx, cfv(ctopn, ccnfld)), ccn, cfv(ctopn, ccnfld))))\n-| diffss(s0, s1)\n-| diffsc(s0, co(nat0, cicc, nat1))\n-| diffsc(s0, cc)\n-| diffsc(s1, co(nat0, cicc, nat1))\n-| diffsc(s1, cc)\n-| wcel(cfv(ctopn, ccnfld), cfv(ctopon, cc))","pretty":"⊢ (s0 ∈(0[[,]]1), s1 ∈(0[[,]]1)↦(s0[×]s1))∈((II[tX]II)[Cn]II)\n⊣ ((II[tX]II)[Cn]II)=((II[tX]II)[Cn]((TopOpen ` CCfld)[|`t](0[[,]]1)))\n⊣ ((s0 ∈(0[[,]]1), s1 ∈(0[[,]]1)↦(s0[×]s1))∈((II[tX]II)[Cn](TopOpen ` CCfld))↔(s0 ∈(0[[,]]1), s1 ∈(0[[,]]1)↦(s0[×]s1))∈((II[tX]II)[Cn]((TopOpen ` CCfld)[|`t](0[[,]]1))))\n⊣ II =((TopOpen ` CCfld)[|`t](0[[,]]1))\n⊣ (T →(0[[,]]1)⊆ ℂ)\n⊣ (T →(s0 ∈ ℂ, s1 ∈ ℂ ↦(s0[×]s1))∈(((TopOpen ` CCfld)[tX](TopOpen ` CCfld))[Cn](TopOpen ` CCfld)))\n⊣ d(s0, s1)\n⊣ d(s0,(0[[,]]1))\n⊣ d(s0, ℂ)\n⊣ d(s1,(0[[,]]1))\n⊣ d(s1, ℂ)\n⊣ (TopOpen ` CCfld)∈(TopOn ` ℂ)"}},{"stmt":{"origin":"a1i(wtru, wss(co(nat0, cicc, nat1), cc))","pretty":"a1i(wtru, (0[[,]]1)⊆ ℂ)"},"body":{"origin":"|- wi(wtru, wss(co(nat0, cicc, nat1), cc))\n-| wss(co(nat0, cicc, nat1), cc)","pretty":"⊢ (T →(0[[,]]1)⊆ ℂ)\n⊣ (0[[,]]1)⊆ ℂ"},"cumulated":{"origin":"|- wcel(cmpo(s0, s1, co(nat0, cicc, nat1), co(nat0, cicc, nat1), co(cv(s0), cmul, cv(s1))), co(co(cii, ctx, cii), ccn, cii))\n-| wceq(co(co(cii, ctx, cii), ccn, cii), co(co(cii, ctx, cii), ccn, co(cfv(ctopn, ccnfld), crest, co(nat0, cicc, nat1))))\n-| wb(wcel(cmpo(s0, s1, co(nat0, cicc, nat1), co(nat0, cicc, nat1), co(cv(s0), cmul, cv(s1))), co(co(cii, ctx, cii), ccn, cfv(ctopn, ccnfld))), wcel(cmpo(s0, s1, co(nat0, cicc, nat1), co(nat0, cicc, nat1), co(cv(s0), cmul, cv(s1))), co(co(cii, ctx, cii), ccn, co(cfv(ctopn, ccnfld), crest, co(nat0, cicc, nat1)))))\n-| wceq(cii, co(cfv(ctopn, ccnfld), crest, co(nat0, cicc, nat1)))\n-| wi(wtru, wcel(cmpo(s0, s1, cc, cc, co(cv(s0), cmul, cv(s1))), co(co(cfv(ctopn, ccnfld), ctx, cfv(ctopn, ccnfld)), ccn, cfv(ctopn, ccnfld))))\n-| diffss(s0, s1)\n-| diffsc(s0, co(nat0, cicc, nat1))\n-| diffsc(s0, cc)\n-| diffsc(s1, co(nat0, cicc, nat1))\n-| diffsc(s1, cc)\n-| wcel(cfv(ctopn, ccnfld), cfv(ctopon, cc))\n-| wss(co(nat0, cicc, nat1), cc)","pretty":"⊢ (s0 ∈(0[[,]]1), s1 ∈(0[[,]]1)↦(s0[×]s1))∈((II[tX]II)[Cn]II)\n⊣ ((II[tX]II)[Cn]II)=((II[tX]II)[Cn]((TopOpen ` CCfld)[|`t](0[[,]]1)))\n⊣ ((s0 ∈(0[[,]]1), s1 ∈(0[[,]]1)↦(s0[×]s1))∈((II[tX]II)[Cn](TopOpen ` CCfld))↔(s0 ∈(0[[,]]1), s1 ∈(0[[,]]1)↦(s0[×]s1))∈((II[tX]II)[Cn]((TopOpen ` CCfld)[|`t](0[[,]]1))))\n⊣ II =((TopOpen ` CCfld)[|`t](0[[,]]1))\n⊣ (T →(s0 ∈ ℂ, s1 ∈ ℂ ↦(s0[×]s1))∈(((TopOpen ` CCfld)[tX](TopOpen ` CCfld))[Cn](TopOpen ` CCfld)))\n⊣ d(s0, s1)\n⊣ d(s0,(0[[,]]1))\n⊣ d(s0, ℂ)\n⊣ d(s1,(0[[,]]1))\n⊣ d(s1, ℂ)\n⊣ (TopOpen ` CCfld)∈(TopOn ` ℂ)\n⊣ (0[[,]]1)⊆ ℂ"}},{"stmt":{"origin":"a1i(wtru, wcel(cmpo(s0, s1, cc, cc, co(cv(s0), cmul, cv(s1))), co(co(cfv(ctopn, ccnfld), ctx, cfv(ctopn, ccnfld)), ccn, cfv(ctopn, ccnfld))))","pretty":"a1i(wtru, (s0 ∈ ℂ, s1 ∈ ℂ ↦(s0[×]s1))∈(((TopOpen ` CCfld)[tX](TopOpen ` CCfld))[Cn](TopOpen ` CCfld)))"},"body":{"origin":"|- wi(wtru, wcel(cmpo(s0, s1, cc, cc, co(cv(s0), cmul, cv(s1))), co(co(cfv(ctopn, ccnfld), ctx, cfv(ctopn, ccnfld)), ccn, cfv(ctopn, ccnfld))))\n-| wcel(cmpo(s0, s1, cc, cc, co(cv(s0), cmul, cv(s1))), co(co(cfv(ctopn, ccnfld), ctx, cfv(ctopn, ccnfld)), ccn, cfv(ctopn, ccnfld)))","pretty":"⊢ (T →(s0 ∈ ℂ, s1 ∈ ℂ ↦(s0[×]s1))∈(((TopOpen ` CCfld)[tX](TopOpen ` CCfld))[Cn](TopOpen ` CCfld)))\n⊣ (s0 ∈ ℂ, s1 ∈ ℂ ↦(s0[×]s1))∈(((TopOpen ` CCfld)[tX](TopOpen ` CCfld))[Cn](TopOpen ` CCfld))"},"cumulated":{"origin":"|- wcel(cmpo(s0, s1, co(nat0, cicc, nat1), co(nat0, cicc, nat1), co(cv(s0), cmul, cv(s1))), co(co(cii, ctx, cii), ccn, cii))\n-| wceq(co(co(cii, ctx, cii), ccn, cii), co(co(cii, ctx, cii), ccn, co(cfv(ctopn, ccnfld), crest, co(nat0, cicc, nat1))))\n-| wb(wcel(cmpo(s0, s1, co(nat0, cicc, nat1), co(nat0, cicc, nat1), co(cv(s0), cmul, cv(s1))), co(co(cii, ctx, cii), ccn, cfv(ctopn, ccnfld))), wcel(cmpo(s0, s1, co(nat0, cicc, nat1), co(nat0, cicc, nat1), co(cv(s0), cmul, cv(s1))), co(co(cii, ctx, cii), ccn, co(cfv(ctopn, ccnfld), crest, co(nat0, cicc, nat1)))))\n-| wceq(cii, co(cfv(ctopn, ccnfld), crest, co(nat0, cicc, nat1)))\n-| diffss(s0, s1)\n-| diffsc(s0, co(nat0, cicc, nat1))\n-| diffsc(s0, cc)\n-| diffsc(s1, co(nat0, cicc, nat1))\n-| diffsc(s1, cc)\n-| wcel(cfv(ctopn, ccnfld), cfv(ctopon, cc))\n-| wss(co(nat0, cicc, nat1), cc)\n-| wcel(cmpo(s0, s1, cc, cc, co(cv(s0), cmul, cv(s1))), co(co(cfv(ctopn, ccnfld), ctx, cfv(ctopn, ccnfld)), ccn, cfv(ctopn, ccnfld)))","pretty":"⊢ (s0 ∈(0[[,]]1), s1 ∈(0[[,]]1)↦(s0[×]s1))∈((II[tX]II)[Cn]II)\n⊣ ((II[tX]II)[Cn]II)=((II[tX]II)[Cn]((TopOpen ` CCfld)[|`t](0[[,]]1)))\n⊣ ((s0 ∈(0[[,]]1), s1 ∈(0[[,]]1)↦(s0[×]s1))∈((II[tX]II)[Cn](TopOpen ` CCfld))↔(s0 ∈(0[[,]]1), s1 ∈(0[[,]]1)↦(s0[×]s1))∈((II[tX]II)[Cn]((TopOpen ` CCfld)[|`t](0[[,]]1))))\n⊣ II =((TopOpen ` CCfld)[|`t](0[[,]]1))\n⊣ d(s0, s1)\n⊣ d(s0,(0[[,]]1))\n⊣ d(s0, ℂ)\n⊣ d(s1,(0[[,]]1))\n⊣ d(s1, ℂ)\n⊣ (TopOpen ` CCfld)∈(TopOn ` ℂ)\n⊣ (0[[,]]1)⊆ ℂ\n⊣ (s0 ∈ ℂ, s1 ∈ ℂ ↦(s0[×]s1))∈(((TopOpen ` CCfld)[tX](TopOpen ` CCfld))[Cn](TopOpen ` CCfld))"}},{"stmt":{"origin":"eqeltrri(cmpo(s0, s1, cc, cc, co(cv(s0), cmul, cv(s1))), co(co(cfv(ctopn, ccnfld), ctx, cfv(ctopn, ccnfld)), ccn, cfv(ctopn, ccnfld)), cmul)","pretty":"eqeltrri((s0 ∈ ℂ, s1 ∈ ℂ ↦(s0[×]s1)), (((TopOpen ` CCfld)[tX](TopOpen ` CCfld))[Cn](TopOpen ` CCfld)), cmul)"},"body":{"origin":"|- wcel(cmpo(s0, s1, cc, cc, co(cv(s0), cmul, cv(s1))), co(co(cfv(ctopn, ccnfld), ctx, cfv(ctopn, ccnfld)), ccn, cfv(ctopn, ccnfld)))\n-| wceq(cmul, cmpo(s0, s1, cc, cc, co(cv(s0), cmul, cv(s1))))\n-| wcel(cmul, co(co(cfv(ctopn, ccnfld), ctx, cfv(ctopn, ccnfld)), ccn, cfv(ctopn, ccnfld)))","pretty":"⊢ (s0 ∈ ℂ, s1 ∈ ℂ ↦(s0[×]s1))∈(((TopOpen ` CCfld)[tX](TopOpen ` CCfld))[Cn](TopOpen ` CCfld))\n⊣ × =(s0 ∈ ℂ, s1 ∈ ℂ ↦(s0[×]s1))\n⊣ × ∈(((TopOpen ` CCfld)[tX](TopOpen ` CCfld))[Cn](TopOpen ` CCfld))"},"cumulated":{"origin":"|- wcel(cmpo(s0, s1, co(nat0, cicc, nat1), co(nat0, cicc, nat1), co(cv(s0), cmul, cv(s1))), co(co(cii, ctx, cii), ccn, cii))\n-| wceq(co(co(cii, ctx, cii), ccn, cii), co(co(cii, ctx, cii), ccn, co(cfv(ctopn, ccnfld), crest, co(nat0, cicc, nat1))))\n-| wb(wcel(cmpo(s0, s1, co(nat0, cicc, nat1), co(nat0, cicc, nat1), co(cv(s0), cmul, cv(s1))), co(co(cii, ctx, cii), ccn, cfv(ctopn, ccnfld))), wcel(cmpo(s0, s1, co(nat0, cicc, nat1), co(nat0, cicc, nat1), co(cv(s0), cmul, cv(s1))), co(co(cii, ctx, cii), ccn, co(cfv(ctopn, ccnfld), crest, co(nat0, cicc, nat1)))))\n-| wceq(cii, co(cfv(ctopn, ccnfld), crest, co(nat0, cicc, nat1)))\n-| diffss(s0, s1)\n-| diffsc(s0, co(nat0, cicc, nat1))\n-| diffsc(s0, cc)\n-| diffsc(s1, co(nat0, cicc, nat1))\n-| diffsc(s1, cc)\n-| wcel(cfv(ctopn, ccnfld), cfv(ctopon, cc))\n-| wss(co(nat0, cicc, nat1), cc)\n-| wceq(cmul, cmpo(s0, s1, cc, cc, co(cv(s0), cmul, cv(s1))))\n-| wcel(cmul, co(co(cfv(ctopn, ccnfld), ctx, cfv(ctopn, ccnfld)), ccn, cfv(ctopn, ccnfld)))","pretty":"⊢ (s0 ∈(0[[,]]1), s1 ∈(0[[,]]1)↦(s0[×]s1))∈((II[tX]II)[Cn]II)\n⊣ ((II[tX]II)[Cn]II)=((II[tX]II)[Cn]((TopOpen ` CCfld)[|`t](0[[,]]1)))\n⊣ ((s0 ∈(0[[,]]1), s1 ∈(0[[,]]1)↦(s0[×]s1))∈((II[tX]II)[Cn](TopOpen ` CCfld))↔(s0 ∈(0[[,]]1), s1 ∈(0[[,]]1)↦(s0[×]s1))∈((II[tX]II)[Cn]((TopOpen ` CCfld)[|`t](0[[,]]1))))\n⊣ II =((TopOpen ` CCfld)[|`t](0[[,]]1))\n⊣ d(s0, s1)\n⊣ d(s0,(0[[,]]1))\n⊣ d(s0, ℂ)\n⊣ d(s1,(0[[,]]1))\n⊣ d(s1, ℂ)\n⊣ (TopOpen ` CCfld)∈(TopOn ` ℂ)\n⊣ (0[[,]]1)⊆ ℂ\n⊣ × =(s0 ∈ ℂ, s1 ∈ ℂ ↦(s0[×]s1))\n⊣ × ∈(((TopOpen ` CCfld)[tX](TopOpen ` CCfld))[Cn](TopOpen ` CCfld))"}},{"stmt":{"origin":"mpbi(wceq(cmul, cmpo(s0, s1, cc, cc, co(cv(s0), cmul, cv(s1)))), wfn(cmul, cxp(cc, cc)))","pretty":"mpbi(× =(s0 ∈ ℂ, s1 ∈ ℂ ↦(s0[×]s1)), ×[Fn](ℂ × ℂ))"},"body":{"origin":"|- wceq(cmul, cmpo(s0, s1, cc, cc, co(cv(s0), cmul, cv(s1))))\n-| wfn(cmul, cxp(cc, cc))\n-| wb(wfn(cmul, cxp(cc, cc)), wceq(cmul, cmpo(s0, s1, cc, cc, co(cv(s0), cmul, cv(s1)))))","pretty":"⊢ × =(s0 ∈ ℂ, s1 ∈ ℂ ↦(s0[×]s1))\n⊣ ×[Fn](ℂ × ℂ)\n⊣ (×[Fn](ℂ × ℂ)↔ × =(s0 ∈ ℂ, s1 ∈ ℂ ↦(s0[×]s1)))"},"cumulated":{"origin":"|- wcel(cmpo(s0, s1, co(nat0, cicc, nat1), co(nat0, cicc, nat1), co(cv(s0), cmul, cv(s1))), co(co(cii, ctx, cii), ccn, cii))\n-| wceq(co(co(cii, ctx, cii), ccn, cii), co(co(cii, ctx, cii), ccn, co(cfv(ctopn, ccnfld), crest, co(nat0, cicc, nat1))))\n-| wb(wcel(cmpo(s0, s1, co(nat0, cicc, nat1), co(nat0, cicc, nat1), co(cv(s0), cmul, cv(s1))), co(co(cii, ctx, cii), ccn, cfv(ctopn, ccnfld))), wcel(cmpo(s0, s1, co(nat0, cicc, nat1), co(nat0, cicc, nat1), co(cv(s0), cmul, cv(s1))), co(co(cii, ctx, cii), ccn, co(cfv(ctopn, ccnfld), crest, co(nat0, cicc, nat1)))))\n-| wceq(cii, co(cfv(ctopn, ccnfld), crest, co(nat0, cicc, nat1)))\n-| diffss(s0, s1)\n-| diffsc(s0, co(nat0, cicc, nat1))\n-| diffsc(s0, cc)\n-| diffsc(s1, co(nat0, cicc, nat1))\n-| diffsc(s1, cc)\n-| wcel(cfv(ctopn, ccnfld), cfv(ctopon, cc))\n-| wss(co(nat0, cicc, nat1), cc)\n-| wcel(cmul, co(co(cfv(ctopn, ccnfld), ctx, cfv(ctopn, ccnfld)), ccn, cfv(ctopn, ccnfld)))\n-| wfn(cmul, cxp(cc, cc))\n-| wb(wfn(cmul, cxp(cc, cc)), wceq(cmul, cmpo(s0, s1, cc, cc, co(cv(s0), cmul, cv(s1)))))","pretty":"⊢ (s0 ∈(0[[,]]1), s1 ∈(0[[,]]1)↦(s0[×]s1))∈((II[tX]II)[Cn]II)\n⊣ ((II[tX]II)[Cn]II)=((II[tX]II)[Cn]((TopOpen ` CCfld)[|`t](0[[,]]1)))\n⊣ ((s0 ∈(0[[,]]1), s1 ∈(0[[,]]1)↦(s0[×]s1))∈((II[tX]II)[Cn](TopOpen ` CCfld))↔(s0 ∈(0[[,]]1), s1 ∈(0[[,]]1)↦(s0[×]s1))∈((II[tX]II)[Cn]((TopOpen ` CCfld)[|`t](0[[,]]1))))\n⊣ II =((TopOpen ` CCfld)[|`t](0[[,]]1))\n⊣ d(s0, s1)\n⊣ d(s0,(0[[,]]1))\n⊣ d(s0, ℂ)\n⊣ d(s1,(0[[,]]1))\n⊣ d(s1, ℂ)\n⊣ (TopOpen ` CCfld)∈(TopOn ` ℂ)\n⊣ (0[[,]]1)⊆ ℂ\n⊣ × ∈(((TopOpen ` CCfld)[tX](TopOpen ` CCfld))[Cn](TopOpen ` CCfld))\n⊣ ×[Fn](ℂ × ℂ)\n⊣ (×[Fn](ℂ × ℂ)↔ × =(s0 ∈ ℂ, s1 ∈ ℂ ↦(s0[×]s1)))"}},{"stmt":{"origin":"ax-mp(wfn(cmul, cxp(cc, cc)), wf(cmul, cxp(cc, cc), cc))","pretty":"ax-mp(×[Fn](ℂ × ℂ), (× :(ℂ × ℂ)→ ℂ))"},"body":{"origin":"|- wfn(cmul, cxp(cc, cc))\n-| wf(cmul, cxp(cc, cc), cc)\n-| wi(wf(cmul, cxp(cc, cc), cc), wfn(cmul, cxp(cc, cc)))","pretty":"⊢ ×[Fn](ℂ × ℂ)\n⊣ (× :(ℂ × ℂ)→ ℂ)\n⊣ ((× :(ℂ × ℂ)→ ℂ)→ ×[Fn](ℂ × ℂ))"},"cumulated":{"origin":"|- wcel(cmpo(s0, s1, co(nat0, cicc, nat1), co(nat0, cicc, nat1), co(cv(s0), cmul, cv(s1))), co(co(cii, ctx, cii), ccn, cii))\n-| wceq(co(co(cii, ctx, cii), ccn, cii), co(co(cii, ctx, cii), ccn, co(cfv(ctopn, ccnfld), crest, co(nat0, cicc, nat1))))\n-| wb(wcel(cmpo(s0, s1, co(nat0, cicc, nat1), co(nat0, cicc, nat1), co(cv(s0), cmul, cv(s1))), co(co(cii, ctx, cii), ccn, cfv(ctopn, ccnfld))), wcel(cmpo(s0, s1, co(nat0, cicc, nat1), co(nat0, cicc, nat1), co(cv(s0), cmul, cv(s1))), co(co(cii, ctx, cii), ccn, co(cfv(ctopn, ccnfld), crest, co(nat0, cicc, nat1)))))\n-| wceq(cii, co(cfv(ctopn, ccnfld), crest, co(nat0, cicc, nat1)))\n-| diffss(s0, s1)\n-| diffsc(s0, co(nat0, cicc, nat1))\n-| diffsc(s0, cc)\n-| diffsc(s1, co(nat0, cicc, nat1))\n-| diffsc(s1, cc)\n-| wcel(cfv(ctopn, ccnfld), cfv(ctopon, cc))\n-| wss(co(nat0, cicc, nat1), cc)\n-| wcel(cmul, co(co(cfv(ctopn, ccnfld), ctx, cfv(ctopn, ccnfld)), ccn, cfv(ctopn, ccnfld)))\n-| wb(wfn(cmul, cxp(cc, cc)), wceq(cmul, cmpo(s0, s1, cc, cc, co(cv(s0), cmul, cv(s1)))))\n-| wf(cmul, cxp(cc, cc), cc)\n-| wi(wf(cmul, cxp(cc, cc), cc), wfn(cmul, cxp(cc, cc)))","pretty":"⊢ (s0 ∈(0[[,]]1), s1 ∈(0[[,]]1)↦(s0[×]s1))∈((II[tX]II)[Cn]II)\n⊣ ((II[tX]II)[Cn]II)=((II[tX]II)[Cn]((TopOpen ` CCfld)[|`t](0[[,]]1)))\n⊣ ((s0 ∈(0[[,]]1), s1 ∈(0[[,]]1)↦(s0[×]s1))∈((II[tX]II)[Cn](TopOpen ` CCfld))↔(s0 ∈(0[[,]]1), s1 ∈(0[[,]]1)↦(s0[×]s1))∈((II[tX]II)[Cn]((TopOpen ` CCfld)[|`t](0[[,]]1))))\n⊣ II =((TopOpen ` CCfld)[|`t](0[[,]]1))\n⊣ d(s0, s1)\n⊣ d(s0,(0[[,]]1))\n⊣ d(s0, ℂ)\n⊣ d(s1,(0[[,]]1))\n⊣ d(s1, ℂ)\n⊣ (TopOpen ` CCfld)∈(TopOn ` ℂ)\n⊣ (0[[,]]1)⊆ ℂ\n⊣ × ∈(((TopOpen ` CCfld)[tX](TopOpen ` CCfld))[Cn](TopOpen ` CCfld))\n⊣ (×[Fn](ℂ × ℂ)↔ × =(s0 ∈ ℂ, s1 ∈ ℂ ↦(s0[×]s1)))\n⊣ (× :(ℂ × ℂ)→ ℂ)\n⊣ ((× :(ℂ × ℂ)→ ℂ)→ ×[Fn](ℂ × ℂ))"}},{"stmt":{"origin":"ax-mulf()","pretty":"ax-mulf()"},"body":{"origin":"|- wf(cmul, cxp(cc, cc), cc)","pretty":"⊢ (× :(ℂ × ℂ)→ ℂ)"},"cumulated":{"origin":"|- wcel(cmpo(s0, s1, co(nat0, cicc, nat1), co(nat0, cicc, nat1), co(cv(s0), cmul, cv(s1))), co(co(cii, ctx, cii), ccn, cii))\n-| wceq(co(co(cii, ctx, cii), ccn, cii), co(co(cii, ctx, cii), ccn, co(cfv(ctopn, ccnfld), crest, co(nat0, cicc, nat1))))\n-| wb(wcel(cmpo(s0, s1, co(nat0, cicc, nat1), co(nat0, cicc, nat1), co(cv(s0), cmul, cv(s1))), co(co(cii, ctx, cii), ccn, cfv(ctopn, ccnfld))), wcel(cmpo(s0, s1, co(nat0, cicc, nat1), co(nat0, cicc, nat1), co(cv(s0), cmul, cv(s1))), co(co(cii, ctx, cii), ccn, co(cfv(ctopn, ccnfld), crest, co(nat0, cicc, nat1)))))\n-| wceq(cii, co(cfv(ctopn, ccnfld), crest, co(nat0, cicc, nat1)))\n-| diffss(s0, s1)\n-| diffsc(s0, co(nat0, cicc, nat1))\n-| diffsc(s0, cc)\n-| diffsc(s1, co(nat0, cicc, nat1))\n-| diffsc(s1, cc)\n-| wcel(cfv(ctopn, ccnfld), cfv(ctopon, cc))\n-| wss(co(nat0, cicc, nat1), cc)\n-| wcel(cmul, co(co(cfv(ctopn, ccnfld), ctx, cfv(ctopn, ccnfld)), ccn, cfv(ctopn, ccnfld)))\n-| wb(wfn(cmul, cxp(cc, cc)), wceq(cmul, cmpo(s0, s1, cc, cc, co(cv(s0), cmul, cv(s1)))))\n-| wi(wf(cmul, cxp(cc, cc), cc), wfn(cmul, cxp(cc, cc)))","pretty":"⊢ (s0 ∈(0[[,]]1), s1 ∈(0[[,]]1)↦(s0[×]s1))∈((II[tX]II)[Cn]II)\n⊣ ((II[tX]II)[Cn]II)=((II[tX]II)[Cn]((TopOpen ` CCfld)[|`t](0[[,]]1)))\n⊣ ((s0 ∈(0[[,]]1), s1 ∈(0[[,]]1)↦(s0[×]s1))∈((II[tX]II)[Cn](TopOpen ` CCfld))↔(s0 ∈(0[[,]]1), s1 ∈(0[[,]]1)↦(s0[×]s1))∈((II[tX]II)[Cn]((TopOpen ` CCfld)[|`t](0[[,]]1))))\n⊣ II =((TopOpen ` CCfld)[|`t](0[[,]]1))\n⊣ d(s0, s1)\n⊣ d(s0,(0[[,]]1))\n⊣ d(s0, ℂ)\n⊣ d(s1,(0[[,]]1))\n⊣ d(s1, ℂ)\n⊣ (TopOpen ` CCfld)∈(TopOn ` ℂ)\n⊣ (0[[,]]1)⊆ ℂ\n⊣ × ∈(((TopOpen ` CCfld)[tX](TopOpen ` CCfld))[Cn](TopOpen ` CCfld))\n⊣ (×[Fn](ℂ × ℂ)↔ × =(s0 ∈ ℂ, s1 ∈ ℂ ↦(s0[×]s1)))\n⊣ ((× :(ℂ × ℂ)→ ℂ)→ ×[Fn](ℂ × ℂ))"}},{"stmt":{"origin":"ffn(cmul, cxp(cc, cc), cc)","pretty":"ffn(cmul, (ℂ × ℂ), cc)"},"body":{"origin":"|- wi(wf(cmul, cxp(cc, cc), cc), wfn(cmul, cxp(cc, cc)))","pretty":"⊢ ((× :(ℂ × ℂ)→ ℂ)→ ×[Fn](ℂ × ℂ))"},"cumulated":{"origin":"|- wcel(cmpo(s0, s1, co(nat0, cicc, nat1), co(nat0, cicc, nat1), co(cv(s0), cmul, cv(s1))), co(co(cii, ctx, cii), ccn, cii))\n-| wceq(co(co(cii, ctx, cii), ccn, cii), co(co(cii, ctx, cii), ccn, co(cfv(ctopn, ccnfld), crest, co(nat0, cicc, nat1))))\n-| wb(wcel(cmpo(s0, s1, co(nat0, cicc, nat1), co(nat0, cicc, nat1), co(cv(s0), cmul, cv(s1))), co(co(cii, ctx, cii), ccn, cfv(ctopn, ccnfld))), wcel(cmpo(s0, s1, co(nat0, cicc, nat1), co(nat0, cicc, nat1), co(cv(s0), cmul, cv(s1))), co(co(cii, ctx, cii), ccn, co(cfv(ctopn, ccnfld), crest, co(nat0, cicc, nat1)))))\n-| wceq(cii, co(cfv(ctopn, ccnfld), crest, co(nat0, cicc, nat1)))\n-| diffss(s0, s1)\n-| diffsc(s0, co(nat0, cicc, nat1))\n-| diffsc(s0, cc)\n-| diffsc(s1, co(nat0, cicc, nat1))\n-| diffsc(s1, cc)\n-| wcel(cfv(ctopn, ccnfld), cfv(ctopon, cc))\n-| wss(co(nat0, cicc, nat1), cc)\n-| wcel(cmul, co(co(cfv(ctopn, ccnfld), ctx, cfv(ctopn, ccnfld)), ccn, cfv(ctopn, ccnfld)))\n-| wb(wfn(cmul, cxp(cc, cc)), wceq(cmul, cmpo(s0, s1, cc, cc, co(cv(s0), cmul, cv(s1)))))","pretty":"⊢ (s0 ∈(0[[,]]1), s1 ∈(0[[,]]1)↦(s0[×]s1))∈((II[tX]II)[Cn]II)\n⊣ ((II[tX]II)[Cn]II)=((II[tX]II)[Cn]((TopOpen ` CCfld)[|`t](0[[,]]1)))\n⊣ ((s0 ∈(0[[,]]1), s1 ∈(0[[,]]1)↦(s0[×]s1))∈((II[tX]II)[Cn](TopOpen ` CCfld))↔(s0 ∈(0[[,]]1), s1 ∈(0[[,]]1)↦(s0[×]s1))∈((II[tX]II)[Cn]((TopOpen ` CCfld)[|`t](0[[,]]1))))\n⊣ II =((TopOpen ` CCfld)[|`t](0[[,]]1))\n⊣ d(s0, s1)\n⊣ d(s0,(0[[,]]1))\n⊣ d(s0, ℂ)\n⊣ d(s1,(0[[,]]1))\n⊣ d(s1, ℂ)\n⊣ (TopOpen ` CCfld)∈(TopOn ` ℂ)\n⊣ (0[[,]]1)⊆ ℂ\n⊣ × ∈(((TopOpen ` CCfld)[tX](TopOpen ` CCfld))[Cn](TopOpen ` CCfld))\n⊣ (×[Fn](ℂ × ℂ)↔ × =(s0 ∈ ℂ, s1 ∈ ℂ ↦(s0[×]s1)))"}},{"stmt":{"origin":"fnov(s0, s1, cmul, cc, cc)","pretty":"fnov(s0, s1, cmul, cc, cc)"},"body":{"origin":"|- wb(wfn(cmul, cxp(cc, cc)), wceq(cmul, cmpo(s0, s1, cc, cc, co(cv(s0), cmul, cv(s1)))))\n-| diffss(s0, s1)\n-| diffsc(s0, cmul)\n-| diffsc(s0, cc)\n-| diffsc(s0, cc)\n-| diffsc(s1, cmul)\n-| diffsc(s1, cc)\n-| diffsc(s1, cc)","pretty":"⊢ (×[Fn](ℂ × ℂ)↔ × =(s0 ∈ ℂ, s1 ∈ ℂ ↦(s0[×]s1)))\n⊣ d(s0, s1)\n⊣ d(s0, ×)\n⊣ d(s0, ℂ)\n⊣ d(s0, ℂ)\n⊣ d(s1, ×)\n⊣ d(s1, ℂ)\n⊣ d(s1, ℂ)"},"cumulated":{"origin":"|- wcel(cmpo(s0, s1, co(nat0, cicc, nat1), co(nat0, cicc, nat1), co(cv(s0), cmul, cv(s1))), co(co(cii, ctx, cii), ccn, cii))\n-| wceq(co(co(cii, ctx, cii), ccn, cii), co(co(cii, ctx, cii), ccn, co(cfv(ctopn, ccnfld), crest, co(nat0, cicc, nat1))))\n-| wb(wcel(cmpo(s0, s1, co(nat0, cicc, nat1), co(nat0, cicc, nat1), co(cv(s0), cmul, cv(s1))), co(co(cii, ctx, cii), ccn, cfv(ctopn, ccnfld))), wcel(cmpo(s0, s1, co(nat0, cicc, nat1), co(nat0, cicc, nat1), co(cv(s0), cmul, cv(s1))), co(co(cii, ctx, cii), ccn, co(cfv(ctopn, ccnfld), crest, co(nat0, cicc, nat1)))))\n-| wceq(cii, co(cfv(ctopn, ccnfld), crest, co(nat0, cicc, nat1)))\n-| diffss(s0, s1)\n-| diffsc(s0, co(nat0, cicc, nat1))\n-| diffsc(s0, cc)\n-| diffsc(s1, co(nat0, cicc, nat1))\n-| diffsc(s1, cc)\n-| wcel(cfv(ctopn, ccnfld), cfv(ctopon, cc))\n-| wss(co(nat0, cicc, nat1), cc)\n-| wcel(cmul, co(co(cfv(ctopn, ccnfld), ctx, cfv(ctopn, ccnfld)), ccn, cfv(ctopn, ccnfld)))\n-| diffsc(s0, cmul)\n-| diffsc(s1, cmul)","pretty":"⊢ (s0 ∈(0[[,]]1), s1 ∈(0[[,]]1)↦(s0[×]s1))∈((II[tX]II)[Cn]II)\n⊣ ((II[tX]II)[Cn]II)=((II[tX]II)[Cn]((TopOpen ` CCfld)[|`t](0[[,]]1)))\n⊣ ((s0 ∈(0[[,]]1), s1 ∈(0[[,]]1)↦(s0[×]s1))∈((II[tX]II)[Cn](TopOpen ` CCfld))↔(s0 ∈(0[[,]]1), s1 ∈(0[[,]]1)↦(s0[×]s1))∈((II[tX]II)[Cn]((TopOpen ` CCfld)[|`t](0[[,]]1))))\n⊣ II =((TopOpen ` CCfld)[|`t](0[[,]]1))\n⊣ d(s0, s1)\n⊣ d(s0,(0[[,]]1))\n⊣ d(s0, ℂ)\n⊣ d(s1,(0[[,]]1))\n⊣ d(s1, ℂ)\n⊣ (TopOpen ` CCfld)∈(TopOn ` ℂ)\n⊣ (0[[,]]1)⊆ ℂ\n⊣ × ∈(((TopOpen ` CCfld)[tX](TopOpen ` CCfld))[Cn](TopOpen ` CCfld))\n⊣ d(s0, ×)\n⊣ d(s1, ×)"}},{"stmt":{"origin":"mulcn(cfv(ctopn, ccnfld))","pretty":"mulcn((TopOpen ` CCfld))"},"body":{"origin":"|- wcel(cmul, co(co(cfv(ctopn, ccnfld), ctx, cfv(ctopn, ccnfld)), ccn, cfv(ctopn, ccnfld)))\n-| wceq(cfv(ctopn, ccnfld), cfv(ctopn, ccnfld))","pretty":"⊢ × ∈(((TopOpen ` CCfld)[tX](TopOpen ` CCfld))[Cn](TopOpen ` CCfld))\n⊣ (TopOpen ` CCfld)=(TopOpen ` CCfld)"},"cumulated":{"origin":"|- wcel(cmpo(s0, s1, co(nat0, cicc, nat1), co(nat0, cicc, nat1), co(cv(s0), cmul, cv(s1))), co(co(cii, ctx, cii), ccn, cii))\n-| wceq(co(co(cii, ctx, cii), ccn, cii), co(co(cii, ctx, cii), ccn, co(cfv(ctopn, ccnfld), crest, co(nat0, cicc, nat1))))\n-| wb(wcel(cmpo(s0, s1, co(nat0, cicc, nat1), co(nat0, cicc, nat1), co(cv(s0), cmul, cv(s1))), co(co(cii, ctx, cii), ccn, cfv(ctopn, ccnfld))), wcel(cmpo(s0, s1, co(nat0, cicc, nat1), co(nat0, cicc, nat1), co(cv(s0), cmul, cv(s1))), co(co(cii, ctx, cii), ccn, co(cfv(ctopn, ccnfld), crest, co(nat0, cicc, nat1)))))\n-| wceq(cii, co(cfv(ctopn, ccnfld), crest, co(nat0, cicc, nat1)))\n-| diffss(s0, s1)\n-| diffsc(s0, co(nat0, cicc, nat1))\n-| diffsc(s0, cc)\n-| diffsc(s1, co(nat0, cicc, nat1))\n-| diffsc(s1, cc)\n-| wcel(cfv(ctopn, ccnfld), cfv(ctopon, cc))\n-| wss(co(nat0, cicc, nat1), cc)\n-| diffsc(s0, cmul)\n-| diffsc(s1, cmul)\n-| wceq(cfv(ctopn, ccnfld), cfv(ctopn, ccnfld))","pretty":"⊢ (s0 ∈(0[[,]]1), s1 ∈(0[[,]]1)↦(s0[×]s1))∈((II[tX]II)[Cn]II)\n⊣ ((II[tX]II)[Cn]II)=((II[tX]II)[Cn]((TopOpen ` CCfld)[|`t](0[[,]]1)))\n⊣ ((s0 ∈(0[[,]]1), s1 ∈(0[[,]]1)↦(s0[×]s1))∈((II[tX]II)[Cn](TopOpen ` CCfld))↔(s0 ∈(0[[,]]1), s1 ∈(0[[,]]1)↦(s0[×]s1))∈((II[tX]II)[Cn]((TopOpen ` CCfld)[|`t](0[[,]]1))))\n⊣ II =((TopOpen ` CCfld)[|`t](0[[,]]1))\n⊣ d(s0, s1)\n⊣ d(s0,(0[[,]]1))\n⊣ d(s0, ℂ)\n⊣ d(s1,(0[[,]]1))\n⊣ d(s1, ℂ)\n⊣ (TopOpen ` CCfld)∈(TopOn ` ℂ)\n⊣ (0[[,]]1)⊆ ℂ\n⊣ d(s0, ×)\n⊣ d(s1, ×)\n⊣ (TopOpen ` CCfld)=(TopOpen ` CCfld)"}},{"stmt":{"origin":"mp3an(wb(wcel(cmpo(s0, s1, co(nat0, cicc, nat1), co(nat0, cicc, nat1), co(cv(s0), cmul, cv(s1))), co(co(cii, ctx, cii), ccn, cfv(ctopn, ccnfld))), wcel(cmpo(s0, s1, co(nat0, cicc, nat1), co(nat0, cicc, nat1), co(cv(s0), cmul, cv(s1))), co(co(cii, ctx, cii), ccn, co(cfv(ctopn, ccnfld), crest, co(nat0, cicc, nat1))))), wcel(cfv(ctopn, ccnfld), cfv(ctopon, cc)), wss(crn(cmpo(s0, s1, co(nat0, cicc, nat1), co(nat0, cicc, nat1), co(cv(s0), cmul, cv(s1)))), co(nat0, cicc, nat1)), wss(co(nat0, cicc, nat1), cc))","pretty":"mp3an(((s0 ∈(0[[,]]1), s1 ∈(0[[,]]1)↦(s0[×]s1))∈((II[tX]II)[Cn](TopOpen ` CCfld))↔(s0 ∈(0[[,]]1), s1 ∈(0[[,]]1)↦(s0[×]s1))∈((II[tX]II)[Cn]((TopOpen ` CCfld)[|`t](0[[,]]1)))), (TopOpen ` CCfld)∈(TopOn ` ℂ), ran((s0 ∈(0[[,]]1), s1 ∈(0[[,]]1)↦(s0[×]s1)))⊆(0[[,]]1), (0[[,]]1)⊆ ℂ)"},"body":{"origin":"|- wb(wcel(cmpo(s0, s1, co(nat0, cicc, nat1), co(nat0, cicc, nat1), co(cv(s0), cmul, cv(s1))), co(co(cii, ctx, cii), ccn, cfv(ctopn, ccnfld))), wcel(cmpo(s0, s1, co(nat0, cicc, nat1), co(nat0, cicc, nat1), co(cv(s0), cmul, cv(s1))), co(co(cii, ctx, cii), ccn, co(cfv(ctopn, ccnfld), crest, co(nat0, cicc, nat1)))))\n-| wcel(cfv(ctopn, ccnfld), cfv(ctopon, cc))\n-| wss(crn(cmpo(s0, s1, co(nat0, cicc, nat1), co(nat0, cicc, nat1), co(cv(s0), cmul, cv(s1)))), co(nat0, cicc, nat1))\n-| wss(co(nat0, cicc, nat1), cc)\n-| wi(w3a(wcel(cfv(ctopn, ccnfld), cfv(ctopon, cc)), wss(crn(cmpo(s0, s1, co(nat0, cicc, nat1), co(nat0, cicc, nat1), co(cv(s0), cmul, cv(s1)))), co(nat0, cicc, nat1)), wss(co(nat0, cicc, nat1), cc)), wb(wcel(cmpo(s0, s1, co(nat0, cicc, nat1), co(nat0, cicc, nat1), co(cv(s0), cmul, cv(s1))), co(co(cii, ctx, cii), ccn, cfv(ctopn, ccnfld))), wcel(cmpo(s0, s1, co(nat0, cicc, nat1), co(nat0, cicc, nat1), co(cv(s0), cmul, cv(s1))), co(co(cii, ctx, cii), ccn, co(cfv(ctopn, ccnfld), crest, co(nat0, cicc, nat1))))))","pretty":"⊢ ((s0 ∈(0[[,]]1), s1 ∈(0[[,]]1)↦(s0[×]s1))∈((II[tX]II)[Cn](TopOpen ` CCfld))↔(s0 ∈(0[[,]]1), s1 ∈(0[[,]]1)↦(s0[×]s1))∈((II[tX]II)[Cn]((TopOpen ` CCfld)[|`t](0[[,]]1))))\n⊣ (TopOpen ` CCfld)∈(TopOn ` ℂ)\n⊣ ran((s0 ∈(0[[,]]1), s1 ∈(0[[,]]1)↦(s0[×]s1)))⊆(0[[,]]1)\n⊣ (0[[,]]1)⊆ ℂ\n⊣ (((TopOpen ` CCfld)∈(TopOn ` ℂ)∧ ran((s0 ∈(0[[,]]1), s1 ∈(0[[,]]1)↦(s0[×]s1)))⊆(0[[,]]1)∧(0[[,]]1)⊆ ℂ)→((s0 ∈(0[[,]]1), s1 ∈(0[[,]]1)↦(s0[×]s1))∈((II[tX]II)[Cn](TopOpen ` CCfld))↔(s0 ∈(0[[,]]1), s1 ∈(0[[,]]1)↦(s0[×]s1))∈((II[tX]II)[Cn]((TopOpen ` CCfld)[|`t](0[[,]]1)))))"},"cumulated":{"origin":"|- wcel(cmpo(s0, s1, co(nat0, cicc, nat1), co(nat0, cicc, nat1), co(cv(s0), cmul, cv(s1))), co(co(cii, ctx, cii), ccn, cii))\n-| wceq(co(co(cii, ctx, cii), ccn, cii), co(co(cii, ctx, cii), ccn, co(cfv(ctopn, ccnfld), crest, co(nat0, cicc, nat1))))\n-| wceq(cii, co(cfv(ctopn, ccnfld), crest, co(nat0, cicc, nat1)))\n-| diffss(s0, s1)\n-| diffsc(s0, co(nat0, cicc, nat1))\n-| diffsc(s0, cc)\n-| diffsc(s1, co(nat0, cicc, nat1))\n-| diffsc(s1, cc)\n-| wcel(cfv(ctopn, ccnfld), cfv(ctopon, cc))\n-| wss(co(nat0, cicc, nat1), cc)\n-| diffsc(s0, cmul)\n-| diffsc(s1, cmul)\n-| wceq(cfv(ctopn, ccnfld), cfv(ctopn, ccnfld))\n-| wss(crn(cmpo(s0, s1, co(nat0, cicc, nat1), co(nat0, cicc, nat1), co(cv(s0), cmul, cv(s1)))), co(nat0, cicc, nat1))\n-| wi(w3a(wcel(cfv(ctopn, ccnfld), cfv(ctopon, cc)), wss(crn(cmpo(s0, s1, co(nat0, cicc, nat1), co(nat0, cicc, nat1), co(cv(s0), cmul, cv(s1)))), co(nat0, cicc, nat1)), wss(co(nat0, cicc, nat1), cc)), wb(wcel(cmpo(s0, s1, co(nat0, cicc, nat1), co(nat0, cicc, nat1), co(cv(s0), cmul, cv(s1))), co(co(cii, ctx, cii), ccn, cfv(ctopn, ccnfld))), wcel(cmpo(s0, s1, co(nat0, cicc, nat1), co(nat0, cicc, nat1), co(cv(s0), cmul, cv(s1))), co(co(cii, ctx, cii), ccn, co(cfv(ctopn, ccnfld), crest, co(nat0, cicc, nat1))))))","pretty":"⊢ (s0 ∈(0[[,]]1), s1 ∈(0[[,]]1)↦(s0[×]s1))∈((II[tX]II)[Cn]II)\n⊣ ((II[tX]II)[Cn]II)=((II[tX]II)[Cn]((TopOpen ` CCfld)[|`t](0[[,]]1)))\n⊣ II =((TopOpen ` CCfld)[|`t](0[[,]]1))\n⊣ d(s0, s1)\n⊣ d(s0,(0[[,]]1))\n⊣ d(s0, ℂ)\n⊣ d(s1,(0[[,]]1))\n⊣ d(s1, ℂ)\n⊣ (TopOpen ` CCfld)∈(TopOn ` ℂ)\n⊣ (0[[,]]1)⊆ ℂ\n⊣ d(s0, ×)\n⊣ d(s1, ×)\n⊣ (TopOpen ` CCfld)=(TopOpen ` CCfld)\n⊣ ran((s0 ∈(0[[,]]1), s1 ∈(0[[,]]1)↦(s0[×]s1)))⊆(0[[,]]1)\n⊣ (((TopOpen ` CCfld)∈(TopOn ` ℂ)∧ ran((s0 ∈(0[[,]]1), s1 ∈(0[[,]]1)↦(s0[×]s1)))⊆(0[[,]]1)∧(0[[,]]1)⊆ ℂ)→((s0 ∈(0[[,]]1), s1 ∈(0[[,]]1)↦(s0[×]s1))∈((II[tX]II)[Cn](TopOpen ` CCfld))↔(s0 ∈(0[[,]]1), s1 ∈(0[[,]]1)↦(s0[×]s1))∈((II[tX]II)[Cn]((TopOpen ` CCfld)[|`t](0[[,]]1)))))"}},{"stmt":{"origin":"cnfldtopon(cfv(ctopn, ccnfld))","pretty":"cnfldtopon((TopOpen ` CCfld))"},"body":{"origin":"|- wcel(cfv(ctopn, ccnfld), cfv(ctopon, cc))\n-| wceq(cfv(ctopn, ccnfld), cfv(ctopn, ccnfld))","pretty":"⊢ (TopOpen ` CCfld)∈(TopOn ` ℂ)\n⊣ (TopOpen ` CCfld)=(TopOpen ` CCfld)"},"cumulated":{"origin":"|- wcel(cmpo(s0, s1, co(nat0, cicc, nat1), co(nat0, cicc, nat1), co(cv(s0), cmul, cv(s1))), co(co(cii, ctx, cii), ccn, cii))\n-| wceq(co(co(cii, ctx, cii), ccn, cii), co(co(cii, ctx, cii), ccn, co(cfv(ctopn, ccnfld), crest, co(nat0, cicc, nat1))))\n-| wceq(cii, co(cfv(ctopn, ccnfld), crest, co(nat0, cicc, nat1)))\n-| diffss(s0, s1)\n-| diffsc(s0, co(nat0, cicc, nat1))\n-| diffsc(s0, cc)\n-| diffsc(s1, co(nat0, cicc, nat1))\n-| diffsc(s1, cc)\n-| wss(co(nat0, cicc, nat1), cc)\n-| diffsc(s0, cmul)\n-| diffsc(s1, cmul)\n-| wceq(cfv(ctopn, ccnfld), cfv(ctopn, ccnfld))\n-| wss(crn(cmpo(s0, s1, co(nat0, cicc, nat1), co(nat0, cicc, nat1), co(cv(s0), cmul, cv(s1)))), co(nat0, cicc, nat1))\n-| wi(w3a(wcel(cfv(ctopn, ccnfld), cfv(ctopon, cc)), wss(crn(cmpo(s0, s1, co(nat0, cicc, nat1), co(nat0, cicc, nat1), co(cv(s0), cmul, cv(s1)))), co(nat0, cicc, nat1)), wss(co(nat0, cicc, nat1), cc)), wb(wcel(cmpo(s0, s1, co(nat0, cicc, nat1), co(nat0, cicc, nat1), co(cv(s0), cmul, cv(s1))), co(co(cii, ctx, cii), ccn, cfv(ctopn, ccnfld))), wcel(cmpo(s0, s1, co(nat0, cicc, nat1), co(nat0, cicc, nat1), co(cv(s0), cmul, cv(s1))), co(co(cii, ctx, cii), ccn, co(cfv(ctopn, ccnfld), crest, co(nat0, cicc, nat1))))))","pretty":"⊢ (s0 ∈(0[[,]]1), s1 ∈(0[[,]]1)↦(s0[×]s1))∈((II[tX]II)[Cn]II)\n⊣ ((II[tX]II)[Cn]II)=((II[tX]II)[Cn]((TopOpen ` CCfld)[|`t](0[[,]]1)))\n⊣ II =((TopOpen ` CCfld)[|`t](0[[,]]1))\n⊣ d(s0, s1)\n⊣ d(s0,(0[[,]]1))\n⊣ d(s0, ℂ)\n⊣ d(s1,(0[[,]]1))\n⊣ d(s1, ℂ)\n⊣ (0[[,]]1)⊆ ℂ\n⊣ d(s0, ×)\n⊣ d(s1, ×)\n⊣ (TopOpen ` CCfld)=(TopOpen ` CCfld)\n⊣ ran((s0 ∈(0[[,]]1), s1 ∈(0[[,]]1)↦(s0[×]s1)))⊆(0[[,]]1)\n⊣ (((TopOpen ` CCfld)∈(TopOn ` ℂ)∧ ran((s0 ∈(0[[,]]1), s1 ∈(0[[,]]1)↦(s0[×]s1)))⊆(0[[,]]1)∧(0[[,]]1)⊆ ℂ)→((s0 ∈(0[[,]]1), s1 ∈(0[[,]]1)↦(s0[×]s1))∈((II[tX]II)[Cn](TopOpen ` CCfld))↔(s0 ∈(0[[,]]1), s1 ∈(0[[,]]1)↦(s0[×]s1))∈((II[tX]II)[Cn]((TopOpen ` CCfld)[|`t](0[[,]]1)))))"}},{"stmt":{"origin":"ax-mp(wss(crn(cmpo(s0, s1, co(nat0, cicc, nat1), co(nat0, cicc, nat1), co(cv(s0), cmul, cv(s1)))), co(nat0, cicc, nat1)), wral(s0, co(nat0, cicc, nat1), wral(s1, co(nat0, cicc, nat1), wcel(co(cv(s0), cmul, cv(s1)), co(nat0, cicc, nat1)))))","pretty":"ax-mp(ran((s0 ∈(0[[,]]1), s1 ∈(0[[,]]1)↦(s0[×]s1)))⊆(0[[,]]1), ∀(s0 ∈(0[[,]]1), ∀(s1 ∈(0[[,]]1),(s0[×]s1)∈(0[[,]]1))))"},"body":{"origin":"|- wss(crn(cmpo(s0, s1, co(nat0, cicc, nat1), co(nat0, cicc, nat1), co(cv(s0), cmul, cv(s1)))), co(nat0, cicc, nat1))\n-| wral(s0, co(nat0, cicc, nat1), wral(s1, co(nat0, cicc, nat1), wcel(co(cv(s0), cmul, cv(s1)), co(nat0, cicc, nat1))))\n-| wi(wral(s0, co(nat0, cicc, nat1), wral(s1, co(nat0, cicc, nat1), wcel(co(cv(s0), cmul, cv(s1)), co(nat0, cicc, nat1)))), wss(crn(cmpo(s0, s1, co(nat0, cicc, nat1), co(nat0, cicc, nat1), co(cv(s0), cmul, cv(s1)))), co(nat0, cicc, nat1)))","pretty":"⊢ ran((s0 ∈(0[[,]]1), s1 ∈(0[[,]]1)↦(s0[×]s1)))⊆(0[[,]]1)\n⊣ ∀(s0 ∈(0[[,]]1), ∀(s1 ∈(0[[,]]1),(s0[×]s1)∈(0[[,]]1)))\n⊣ (∀(s0 ∈(0[[,]]1), ∀(s1 ∈(0[[,]]1),(s0[×]s1)∈(0[[,]]1)))→ ran((s0 ∈(0[[,]]1), s1 ∈(0[[,]]1)↦(s0[×]s1)))⊆(0[[,]]1))"},"cumulated":{"origin":"|- wcel(cmpo(s0, s1, co(nat0, cicc, nat1), co(nat0, cicc, nat1), co(cv(s0), cmul, cv(s1))), co(co(cii, ctx, cii), ccn, cii))\n-| wceq(co(co(cii, ctx, cii), ccn, cii), co(co(cii, ctx, cii), ccn, co(cfv(ctopn, ccnfld), crest, co(nat0, cicc, nat1))))\n-| wceq(cii, co(cfv(ctopn, ccnfld), crest, co(nat0, cicc, nat1)))\n-| diffss(s0, s1)\n-| diffsc(s0, co(nat0, cicc, nat1))\n-| diffsc(s0, cc)\n-| diffsc(s1, co(nat0, cicc, nat1))\n-| diffsc(s1, cc)\n-| wss(co(nat0, cicc, nat1), cc)\n-| diffsc(s0, cmul)\n-| diffsc(s1, cmul)\n-| wceq(cfv(ctopn, ccnfld), cfv(ctopn, ccnfld))\n-| wi(w3a(wcel(cfv(ctopn, ccnfld), cfv(ctopon, cc)), wss(crn(cmpo(s0, s1, co(nat0, cicc, nat1), co(nat0, cicc, nat1), co(cv(s0), cmul, cv(s1)))), co(nat0, cicc, nat1)), wss(co(nat0, cicc, nat1), cc)), wb(wcel(cmpo(s0, s1, co(nat0, cicc, nat1), co(nat0, cicc, nat1), co(cv(s0), cmul, cv(s1))), co(co(cii, ctx, cii), ccn, cfv(ctopn, ccnfld))), wcel(cmpo(s0, s1, co(nat0, cicc, nat1), co(nat0, cicc, nat1), co(cv(s0), cmul, cv(s1))), co(co(cii, ctx, cii), ccn, co(cfv(ctopn, ccnfld), crest, co(nat0, cicc, nat1))))))\n-| wral(s0, co(nat0, cicc, nat1), wral(s1, co(nat0, cicc, nat1), wcel(co(cv(s0), cmul, cv(s1)), co(nat0, cicc, nat1))))\n-| wi(wral(s0, co(nat0, cicc, nat1), wral(s1, co(nat0, cicc, nat1), wcel(co(cv(s0), cmul, cv(s1)), co(nat0, cicc, nat1)))), wss(crn(cmpo(s0, s1, co(nat0, cicc, nat1), co(nat0, cicc, nat1), co(cv(s0), cmul, cv(s1)))), co(nat0, cicc, nat1)))","pretty":"⊢ (s0 ∈(0[[,]]1), s1 ∈(0[[,]]1)↦(s0[×]s1))∈((II[tX]II)[Cn]II)\n⊣ ((II[tX]II)[Cn]II)=((II[tX]II)[Cn]((TopOpen ` CCfld)[|`t](0[[,]]1)))\n⊣ II =((TopOpen ` CCfld)[|`t](0[[,]]1))\n⊣ d(s0, s1)\n⊣ d(s0,(0[[,]]1))\n⊣ d(s0, ℂ)\n⊣ d(s1,(0[[,]]1))\n⊣ d(s1, ℂ)\n⊣ (0[[,]]1)⊆ ℂ\n⊣ d(s0, ×)\n⊣ d(s1, ×)\n⊣ (TopOpen ` CCfld)=(TopOpen ` CCfld)\n⊣ (((TopOpen ` CCfld)∈(TopOn ` ℂ)∧ ran((s0 ∈(0[[,]]1), s1 ∈(0[[,]]1)↦(s0[×]s1)))⊆(0[[,]]1)∧(0[[,]]1)⊆ ℂ)→((s0 ∈(0[[,]]1), s1 ∈(0[[,]]1)↦(s0[×]s1))∈((II[tX]II)[Cn](TopOpen ` CCfld))↔(s0 ∈(0[[,]]1), s1 ∈(0[[,]]1)↦(s0[×]s1))∈((II[tX]II)[Cn]((TopOpen ` CCfld)[|`t](0[[,]]1)))))\n⊣ ∀(s0 ∈(0[[,]]1), ∀(s1 ∈(0[[,]]1),(s0[×]s1)∈(0[[,]]1)))\n⊣ (∀(s0 ∈(0[[,]]1), ∀(s1 ∈(0[[,]]1),(s0[×]s1)∈(0[[,]]1)))→ ran((s0 ∈(0[[,]]1), s1 ∈(0[[,]]1)↦(s0[×]s1)))⊆(0[[,]]1))"}},{"stmt":{"origin":"rgen2a(s0, s1, co(nat0, cicc, nat1), wcel(co(cv(s0), cmul, cv(s1)), co(nat0, cicc, nat1)))","pretty":"rgen2a(s0, s1, (0[[,]]1), (s0[×]s1)∈(0[[,]]1))"},"body":{"origin":"|- wral(s0, co(nat0, cicc, nat1), wral(s1, co(nat0, cicc, nat1), wcel(co(cv(s0), cmul, cv(s1)), co(nat0, cicc, nat1))))\n-| wi(wa(wcel(cv(s0), co(nat0, cicc, nat1)), wcel(cv(s1), co(nat0, cicc, nat1))), wcel(co(cv(s0), cmul, cv(s1)), co(nat0, cicc, nat1)))\n-| diffsc(s1, co(nat0, cicc, nat1))","pretty":"⊢ ∀(s0 ∈(0[[,]]1), ∀(s1 ∈(0[[,]]1),(s0[×]s1)∈(0[[,]]1)))\n⊣ ((s0 ∈(0[[,]]1)∧ s1 ∈(0[[,]]1))→(s0[×]s1)∈(0[[,]]1))\n⊣ d(s1,(0[[,]]1))"},"cumulated":{"origin":"|- wcel(cmpo(s0, s1, co(nat0, cicc, nat1), co(nat0, cicc, nat1), co(cv(s0), cmul, cv(s1))), co(co(cii, ctx, cii), ccn, cii))\n-| wceq(co(co(cii, ctx, cii), ccn, cii), co(co(cii, ctx, cii), ccn, co(cfv(ctopn, ccnfld), crest, co(nat0, cicc, nat1))))\n-| wceq(cii, co(cfv(ctopn, ccnfld), crest, co(nat0, cicc, nat1)))\n-| diffss(s0, s1)\n-| diffsc(s0, co(nat0, cicc, nat1))\n-| diffsc(s0, cc)\n-| diffsc(s1, co(nat0, cicc, nat1))\n-| diffsc(s1, cc)\n-| wss(co(nat0, cicc, nat1), cc)\n-| diffsc(s0, cmul)\n-| diffsc(s1, cmul)\n-| wceq(cfv(ctopn, ccnfld), cfv(ctopn, ccnfld))\n-| wi(w3a(wcel(cfv(ctopn, ccnfld), cfv(ctopon, cc)), wss(crn(cmpo(s0, s1, co(nat0, cicc, nat1), co(nat0, cicc, nat1), co(cv(s0), cmul, cv(s1)))), co(nat0, cicc, nat1)), wss(co(nat0, cicc, nat1), cc)), wb(wcel(cmpo(s0, s1, co(nat0, cicc, nat1), co(nat0, cicc, nat1), co(cv(s0), cmul, cv(s1))), co(co(cii, ctx, cii), ccn, cfv(ctopn, ccnfld))), wcel(cmpo(s0, s1, co(nat0, cicc, nat1), co(nat0, cicc, nat1), co(cv(s0), cmul, cv(s1))), co(co(cii, ctx, cii), ccn, co(cfv(ctopn, ccnfld), crest, co(nat0, cicc, nat1))))))\n-| wi(wral(s0, co(nat0, cicc, nat1), wral(s1, co(nat0, cicc, nat1), wcel(co(cv(s0), cmul, cv(s1)), co(nat0, cicc, nat1)))), wss(crn(cmpo(s0, s1, co(nat0, cicc, nat1), co(nat0, cicc, nat1), co(cv(s0), cmul, cv(s1)))), co(nat0, cicc, nat1)))\n-| wi(wa(wcel(cv(s0), co(nat0, cicc, nat1)), wcel(cv(s1), co(nat0, cicc, nat1))), wcel(co(cv(s0), cmul, cv(s1)), co(nat0, cicc, nat1)))","pretty":"⊢ (s0 ∈(0[[,]]1), s1 ∈(0[[,]]1)↦(s0[×]s1))∈((II[tX]II)[Cn]II)\n⊣ ((II[tX]II)[Cn]II)=((II[tX]II)[Cn]((TopOpen ` CCfld)[|`t](0[[,]]1)))\n⊣ II =((TopOpen ` CCfld)[|`t](0[[,]]1))\n⊣ d(s0, s1)\n⊣ d(s0,(0[[,]]1))\n⊣ d(s0, ℂ)\n⊣ d(s1,(0[[,]]1))\n⊣ d(s1, ℂ)\n⊣ (0[[,]]1)⊆ ℂ\n⊣ d(s0, ×)\n⊣ d(s1, ×)\n⊣ (TopOpen ` CCfld)=(TopOpen ` CCfld)\n⊣ (((TopOpen ` CCfld)∈(TopOn ` ℂ)∧ ran((s0 ∈(0[[,]]1), s1 ∈(0[[,]]1)↦(s0[×]s1)))⊆(0[[,]]1)∧(0[[,]]1)⊆ ℂ)→((s0 ∈(0[[,]]1), s1 ∈(0[[,]]1)↦(s0[×]s1))∈((II[tX]II)[Cn](TopOpen ` CCfld))↔(s0 ∈(0[[,]]1), s1 ∈(0[[,]]1)↦(s0[×]s1))∈((II[tX]II)[Cn]((TopOpen ` CCfld)[|`t](0[[,]]1)))))\n⊣ (∀(s0 ∈(0[[,]]1), ∀(s1 ∈(0[[,]]1),(s0[×]s1)∈(0[[,]]1)))→ ran((s0 ∈(0[[,]]1), s1 ∈(0[[,]]1)↦(s0[×]s1)))⊆(0[[,]]1))\n⊣ ((s0 ∈(0[[,]]1)∧ s1 ∈(0[[,]]1))→(s0[×]s1)∈(0[[,]]1))"}},{"stmt":{"origin":"iimulcl(cv(s0), cv(s1))","pretty":"iimulcl(s0, s1)"},"body":{"origin":"|- wi(wa(wcel(cv(s0), co(nat0, cicc, nat1)), wcel(cv(s1), co(nat0, cicc, nat1))), wcel(co(cv(s0), cmul, cv(s1)), co(nat0, cicc, nat1)))","pretty":"⊢ ((s0 ∈(0[[,]]1)∧ s1 ∈(0[[,]]1))→(s0[×]s1)∈(0[[,]]1))"},"cumulated":{"origin":"|- wcel(cmpo(s0, s1, co(nat0, cicc, nat1), co(nat0, cicc, nat1), co(cv(s0), cmul, cv(s1))), co(co(cii, ctx, cii), ccn, cii))\n-| wceq(co(co(cii, ctx, cii), ccn, cii), co(co(cii, ctx, cii), ccn, co(cfv(ctopn, ccnfld), crest, co(nat0, cicc, nat1))))\n-| wceq(cii, co(cfv(ctopn, ccnfld), crest, co(nat0, cicc, nat1)))\n-| diffss(s0, s1)\n-| diffsc(s0, co(nat0, cicc, nat1))\n-| diffsc(s0, cc)\n-| diffsc(s1, co(nat0, cicc, nat1))\n-| diffsc(s1, cc)\n-| wss(co(nat0, cicc, nat1), cc)\n-| diffsc(s0, cmul)\n-| diffsc(s1, cmul)\n-| wceq(cfv(ctopn, ccnfld), cfv(ctopn, ccnfld))\n-| wi(w3a(wcel(cfv(ctopn, ccnfld), cfv(ctopon, cc)), wss(crn(cmpo(s0, s1, co(nat0, cicc, nat1), co(nat0, cicc, nat1), co(cv(s0), cmul, cv(s1)))), co(nat0, cicc, nat1)), wss(co(nat0, cicc, nat1), cc)), wb(wcel(cmpo(s0, s1, co(nat0, cicc, nat1), co(nat0, cicc, nat1), co(cv(s0), cmul, cv(s1))), co(co(cii, ctx, cii), ccn, cfv(ctopn, ccnfld))), wcel(cmpo(s0, s1, co(nat0, cicc, nat1), co(nat0, cicc, nat1), co(cv(s0), cmul, cv(s1))), co(co(cii, ctx, cii), ccn, co(cfv(ctopn, ccnfld), crest, co(nat0, cicc, nat1))))))\n-| wi(wral(s0, co(nat0, cicc, nat1), wral(s1, co(nat0, cicc, nat1), wcel(co(cv(s0), cmul, cv(s1)), co(nat0, cicc, nat1)))), wss(crn(cmpo(s0, s1, co(nat0, cicc, nat1), co(nat0, cicc, nat1), co(cv(s0), cmul, cv(s1)))), co(nat0, cicc, nat1)))","pretty":"⊢ (s0 ∈(0[[,]]1), s1 ∈(0[[,]]1)↦(s0[×]s1))∈((II[tX]II)[Cn]II)\n⊣ ((II[tX]II)[Cn]II)=((II[tX]II)[Cn]((TopOpen ` CCfld)[|`t](0[[,]]1)))\n⊣ II =((TopOpen ` CCfld)[|`t](0[[,]]1))\n⊣ d(s0, s1)\n⊣ d(s0,(0[[,]]1))\n⊣ d(s0, ℂ)\n⊣ d(s1,(0[[,]]1))\n⊣ d(s1, ℂ)\n⊣ (0[[,]]1)⊆ ℂ\n⊣ d(s0, ×)\n⊣ d(s1, ×)\n⊣ (TopOpen ` CCfld)=(TopOpen ` CCfld)\n⊣ (((TopOpen ` CCfld)∈(TopOn ` ℂ)∧ ran((s0 ∈(0[[,]]1), s1 ∈(0[[,]]1)↦(s0[×]s1)))⊆(0[[,]]1)∧(0[[,]]1)⊆ ℂ)→((s0 ∈(0[[,]]1), s1 ∈(0[[,]]1)↦(s0[×]s1))∈((II[tX]II)[Cn](TopOpen ` CCfld))↔(s0 ∈(0[[,]]1), s1 ∈(0[[,]]1)↦(s0[×]s1))∈((II[tX]II)[Cn]((TopOpen ` CCfld)[|`t](0[[,]]1)))))\n⊣ (∀(s0 ∈(0[[,]]1), ∀(s1 ∈(0[[,]]1),(s0[×]s1)∈(0[[,]]1)))→ ran((s0 ∈(0[[,]]1), s1 ∈(0[[,]]1)↦(s0[×]s1)))⊆(0[[,]]1))"}},{"stmt":{"origin":"sylbi(wral(s0, co(nat0, cicc, nat1), wral(s1, co(nat0, cicc, nat1), wcel(co(cv(s0), cmul, cv(s1)), co(nat0, cicc, nat1)))), wss(crn(cmpo(s0, s1, co(nat0, cicc, nat1), co(nat0, cicc, nat1), co(cv(s0), cmul, cv(s1)))), co(nat0, cicc, nat1)), wf(cmpo(s0, s1, co(nat0, cicc, nat1), co(nat0, cicc, nat1), co(cv(s0), cmul, cv(s1))), cxp(co(nat0, cicc, nat1), co(nat0, cicc, nat1)), co(nat0, cicc, nat1)))","pretty":"sylbi(∀(s0 ∈(0[[,]]1), ∀(s1 ∈(0[[,]]1),(s0[×]s1)∈(0[[,]]1))), ran((s0 ∈(0[[,]]1), s1 ∈(0[[,]]1)↦(s0[×]s1)))⊆(0[[,]]1), ((s0 ∈(0[[,]]1), s1 ∈(0[[,]]1)↦(s0[×]s1)):((0[[,]]1)×(0[[,]]1))→(0[[,]]1)))"},"body":{"origin":"|- wi(wral(s0, co(nat0, cicc, nat1), wral(s1, co(nat0, cicc, nat1), wcel(co(cv(s0), cmul, cv(s1)), co(nat0, cicc, nat1)))), wss(crn(cmpo(s0, s1, co(nat0, cicc, nat1), co(nat0, cicc, nat1), co(cv(s0), cmul, cv(s1)))), co(nat0, cicc, nat1)))\n-| wb(wral(s0, co(nat0, cicc, nat1), wral(s1, co(nat0, cicc, nat1), wcel(co(cv(s0), cmul, cv(s1)), co(nat0, cicc, nat1)))), wf(cmpo(s0, s1, co(nat0, cicc, nat1), co(nat0, cicc, nat1), co(cv(s0), cmul, cv(s1))), cxp(co(nat0, cicc, nat1), co(nat0, cicc, nat1)), co(nat0, cicc, nat1)))\n-| wi(wf(cmpo(s0, s1, co(nat0, cicc, nat1), co(nat0, cicc, nat1), co(cv(s0), cmul, cv(s1))), cxp(co(nat0, cicc, nat1), co(nat0, cicc, nat1)), co(nat0, cicc, nat1)), wss(crn(cmpo(s0, s1, co(nat0, cicc, nat1), co(nat0, cicc, nat1), co(cv(s0), cmul, cv(s1)))), co(nat0, cicc, nat1)))","pretty":"⊢ (∀(s0 ∈(0[[,]]1), ∀(s1 ∈(0[[,]]1),(s0[×]s1)∈(0[[,]]1)))→ ran((s0 ∈(0[[,]]1), s1 ∈(0[[,]]1)↦(s0[×]s1)))⊆(0[[,]]1))\n⊣ (∀(s0 ∈(0[[,]]1), ∀(s1 ∈(0[[,]]1),(s0[×]s1)∈(0[[,]]1)))↔((s0 ∈(0[[,]]1), s1 ∈(0[[,]]1)↦(s0[×]s1)):((0[[,]]1)×(0[[,]]1))→(0[[,]]1)))\n⊣ (((s0 ∈(0[[,]]1), s1 ∈(0[[,]]1)↦(s0[×]s1)):((0[[,]]1)×(0[[,]]1))→(0[[,]]1))→ ran((s0 ∈(0[[,]]1), s1 ∈(0[[,]]1)↦(s0[×]s1)))⊆(0[[,]]1))"},"cumulated":{"origin":"|- wcel(cmpo(s0, s1, co(nat0, cicc, nat1), co(nat0, cicc, nat1), co(cv(s0), cmul, cv(s1))), co(co(cii, ctx, cii), ccn, cii))\n-| wceq(co(co(cii, ctx, cii), ccn, cii), co(co(cii, ctx, cii), ccn, co(cfv(ctopn, ccnfld), crest, co(nat0, cicc, nat1))))\n-| wceq(cii, co(cfv(ctopn, ccnfld), crest, co(nat0, cicc, nat1)))\n-| diffss(s0, s1)\n-| diffsc(s0, co(nat0, cicc, nat1))\n-| diffsc(s0, cc)\n-| diffsc(s1, co(nat0, cicc, nat1))\n-| diffsc(s1, cc)\n-| wss(co(nat0, cicc, nat1), cc)\n-| diffsc(s0, cmul)\n-| diffsc(s1, cmul)\n-| wceq(cfv(ctopn, ccnfld), cfv(ctopn, ccnfld))\n-| wi(w3a(wcel(cfv(ctopn, ccnfld), cfv(ctopon, cc)), wss(crn(cmpo(s0, s1, co(nat0, cicc, nat1), co(nat0, cicc, nat1), co(cv(s0), cmul, cv(s1)))), co(nat0, cicc, nat1)), wss(co(nat0, cicc, nat1), cc)), wb(wcel(cmpo(s0, s1, co(nat0, cicc, nat1), co(nat0, cicc, nat1), co(cv(s0), cmul, cv(s1))), co(co(cii, ctx, cii), ccn, cfv(ctopn, ccnfld))), wcel(cmpo(s0, s1, co(nat0, cicc, nat1), co(nat0, cicc, nat1), co(cv(s0), cmul, cv(s1))), co(co(cii, ctx, cii), ccn, co(cfv(ctopn, ccnfld), crest, co(nat0, cicc, nat1))))))\n-| wb(wral(s0, co(nat0, cicc, nat1), wral(s1, co(nat0, cicc, nat1), wcel(co(cv(s0), cmul, cv(s1)), co(nat0, cicc, nat1)))), wf(cmpo(s0, s1, co(nat0, cicc, nat1), co(nat0, cicc, nat1), co(cv(s0), cmul, cv(s1))), cxp(co(nat0, cicc, nat1), co(nat0, cicc, nat1)), co(nat0, cicc, nat1)))\n-| wi(wf(cmpo(s0, s1, co(nat0, cicc, nat1), co(nat0, cicc, nat1), co(cv(s0), cmul, cv(s1))), cxp(co(nat0, cicc, nat1), co(nat0, cicc, nat1)), co(nat0, cicc, nat1)), wss(crn(cmpo(s0, s1, co(nat0, cicc, nat1), co(nat0, cicc, nat1), co(cv(s0), cmul, cv(s1)))), co(nat0, cicc, nat1)))","pretty":"⊢ (s0 ∈(0[[,]]1), s1 ∈(0[[,]]1)↦(s0[×]s1))∈((II[tX]II)[Cn]II)\n⊣ ((II[tX]II)[Cn]II)=((II[tX]II)[Cn]((TopOpen ` CCfld)[|`t](0[[,]]1)))\n⊣ II =((TopOpen ` CCfld)[|`t](0[[,]]1))\n⊣ d(s0, s1)\n⊣ d(s0,(0[[,]]1))\n⊣ d(s0, ℂ)\n⊣ d(s1,(0[[,]]1))\n⊣ d(s1, ℂ)\n⊣ (0[[,]]1)⊆ ℂ\n⊣ d(s0, ×)\n⊣ d(s1, ×)\n⊣ (TopOpen ` CCfld)=(TopOpen ` CCfld)\n⊣ (((TopOpen ` CCfld)∈(TopOn ` ℂ)∧ ran((s0 ∈(0[[,]]1), s1 ∈(0[[,]]1)↦(s0[×]s1)))⊆(0[[,]]1)∧(0[[,]]1)⊆ ℂ)→((s0 ∈(0[[,]]1), s1 ∈(0[[,]]1)↦(s0[×]s1))∈((II[tX]II)[Cn](TopOpen ` CCfld))↔(s0 ∈(0[[,]]1), s1 ∈(0[[,]]1)↦(s0[×]s1))∈((II[tX]II)[Cn]((TopOpen ` CCfld)[|`t](0[[,]]1)))))\n⊣ (∀(s0 ∈(0[[,]]1), ∀(s1 ∈(0[[,]]1),(s0[×]s1)∈(0[[,]]1)))↔((s0 ∈(0[[,]]1), s1 ∈(0[[,]]1)↦(s0[×]s1)):((0[[,]]1)×(0[[,]]1))→(0[[,]]1)))\n⊣ (((s0 ∈(0[[,]]1), s1 ∈(0[[,]]1)↦(s0[×]s1)):((0[[,]]1)×(0[[,]]1))→(0[[,]]1))→ ran((s0 ∈(0[[,]]1), s1 ∈(0[[,]]1)↦(s0[×]s1)))⊆(0[[,]]1))"}},{"stmt":{"origin":"fmpt2(s0, s1, co(nat0, cicc, nat1), co(nat0, cicc, nat1), co(cv(s0), cmul, cv(s1)), co(nat0, cicc, nat1), cmpo(s0, s1, co(nat0, cicc, nat1), co(nat0, cicc, nat1), co(cv(s0), cmul, cv(s1))))","pretty":"fmpt2(s0, s1, (0[[,]]1), (0[[,]]1), (s0[×]s1), (0[[,]]1), (s0 ∈(0[[,]]1), s1 ∈(0[[,]]1)↦(s0[×]s1)))"},"body":{"origin":"|- wb(wral(s0, co(nat0, cicc, nat1), wral(s1, co(nat0, cicc, nat1), wcel(co(cv(s0), cmul, cv(s1)), co(nat0, cicc, nat1)))), wf(cmpo(s0, s1, co(nat0, cicc, nat1), co(nat0, cicc, nat1), co(cv(s0), cmul, cv(s1))), cxp(co(nat0, cicc, nat1), co(nat0, cicc, nat1)), co(nat0, cicc, nat1)))\n-| wceq(cmpo(s0, s1, co(nat0, cicc, nat1), co(nat0, cicc, nat1), co(cv(s0), cmul, cv(s1))), cmpo(s0, s1, co(nat0, cicc, nat1), co(nat0, cicc, nat1), co(cv(s0), cmul, cv(s1))))\n-| diffss(s0, s1)\n-| diffsc(s0, co(nat0, cicc, nat1))\n-| diffsc(s0, co(nat0, cicc, nat1))\n-| diffsc(s0, co(nat0, cicc, nat1))\n-| diffsc(s1, co(nat0, cicc, nat1))\n-| diffsc(s1, co(nat0, cicc, nat1))\n-| diffsc(s1, co(nat0, cicc, nat1))","pretty":"⊢ (∀(s0 ∈(0[[,]]1), ∀(s1 ∈(0[[,]]1),(s0[×]s1)∈(0[[,]]1)))↔((s0 ∈(0[[,]]1), s1 ∈(0[[,]]1)↦(s0[×]s1)):((0[[,]]1)×(0[[,]]1))→(0[[,]]1)))\n⊣ (s0 ∈(0[[,]]1), s1 ∈(0[[,]]1)↦(s0[×]s1))=(s0 ∈(0[[,]]1), s1 ∈(0[[,]]1)↦(s0[×]s1))\n⊣ d(s0, s1)\n⊣ d(s0,(0[[,]]1))\n⊣ d(s0,(0[[,]]1))\n⊣ d(s0,(0[[,]]1))\n⊣ d(s1,(0[[,]]1))\n⊣ d(s1,(0[[,]]1))\n⊣ d(s1,(0[[,]]1))"},"cumulated":{"origin":"|- wcel(cmpo(s0, s1, co(nat0, cicc, nat1), co(nat0, cicc, nat1), co(cv(s0), cmul, cv(s1))), co(co(cii, ctx, cii), ccn, cii))\n-| wceq(co(co(cii, ctx, cii), ccn, cii), co(co(cii, ctx, cii), ccn, co(cfv(ctopn, ccnfld), crest, co(nat0, cicc, nat1))))\n-| wceq(cii, co(cfv(ctopn, ccnfld), crest, co(nat0, cicc, nat1)))\n-| diffss(s0, s1)\n-| diffsc(s0, co(nat0, cicc, nat1))\n-| diffsc(s0, cc)\n-| diffsc(s1, co(nat0, cicc, nat1))\n-| diffsc(s1, cc)\n-| wss(co(nat0, cicc, nat1), cc)\n-| diffsc(s0, cmul)\n-| diffsc(s1, cmul)\n-| wceq(cfv(ctopn, ccnfld), cfv(ctopn, ccnfld))\n-| wi(w3a(wcel(cfv(ctopn, ccnfld), cfv(ctopon, cc)), wss(crn(cmpo(s0, s1, co(nat0, cicc, nat1), co(nat0, cicc, nat1), co(cv(s0), cmul, cv(s1)))), co(nat0, cicc, nat1)), wss(co(nat0, cicc, nat1), cc)), wb(wcel(cmpo(s0, s1, co(nat0, cicc, nat1), co(nat0, cicc, nat1), co(cv(s0), cmul, cv(s1))), co(co(cii, ctx, cii), ccn, cfv(ctopn, ccnfld))), wcel(cmpo(s0, s1, co(nat0, cicc, nat1), co(nat0, cicc, nat1), co(cv(s0), cmul, cv(s1))), co(co(cii, ctx, cii), ccn, co(cfv(ctopn, ccnfld), crest, co(nat0, cicc, nat1))))))\n-| wi(wf(cmpo(s0, s1, co(nat0, cicc, nat1), co(nat0, cicc, nat1), co(cv(s0), cmul, cv(s1))), cxp(co(nat0, cicc, nat1), co(nat0, cicc, nat1)), co(nat0, cicc, nat1)), wss(crn(cmpo(s0, s1, co(nat0, cicc, nat1), co(nat0, cicc, nat1), co(cv(s0), cmul, cv(s1)))), co(nat0, cicc, nat1)))\n-| wceq(cmpo(s0, s1, co(nat0, cicc, nat1), co(nat0, cicc, nat1), co(cv(s0), cmul, cv(s1))), cmpo(s0, s1, co(nat0, cicc, nat1), co(nat0, cicc, nat1), co(cv(s0), cmul, cv(s1))))","pretty":"⊢ (s0 ∈(0[[,]]1), s1 ∈(0[[,]]1)↦(s0[×]s1))∈((II[tX]II)[Cn]II)\n⊣ ((II[tX]II)[Cn]II)=((II[tX]II)[Cn]((TopOpen ` CCfld)[|`t](0[[,]]1)))\n⊣ II =((TopOpen ` CCfld)[|`t](0[[,]]1))\n⊣ d(s0, s1)\n⊣ d(s0,(0[[,]]1))\n⊣ d(s0, ℂ)\n⊣ d(s1,(0[[,]]1))\n⊣ d(s1, ℂ)\n⊣ (0[[,]]1)⊆ ℂ\n⊣ d(s0, ×)\n⊣ d(s1, ×)\n⊣ (TopOpen ` CCfld)=(TopOpen ` CCfld)\n⊣ (((TopOpen ` CCfld)∈(TopOn ` ℂ)∧ ran((s0 ∈(0[[,]]1), s1 ∈(0[[,]]1)↦(s0[×]s1)))⊆(0[[,]]1)∧(0[[,]]1)⊆ ℂ)→((s0 ∈(0[[,]]1), s1 ∈(0[[,]]1)↦(s0[×]s1))∈((II[tX]II)[Cn](TopOpen ` CCfld))↔(s0 ∈(0[[,]]1), s1 ∈(0[[,]]1)↦(s0[×]s1))∈((II[tX]II)[Cn]((TopOpen ` CCfld)[|`t](0[[,]]1)))))\n⊣ (((s0 ∈(0[[,]]1), s1 ∈(0[[,]]1)↦(s0[×]s1)):((0[[,]]1)×(0[[,]]1))→(0[[,]]1))→ ran((s0 ∈(0[[,]]1), s1 ∈(0[[,]]1)↦(s0[×]s1)))⊆(0[[,]]1))\n⊣ (s0 ∈(0[[,]]1), s1 ∈(0[[,]]1)↦(s0[×]s1))=(s0 ∈(0[[,]]1), s1 ∈(0[[,]]1)↦(s0[×]s1))"}},{"stmt":{"origin":"eqid(cmpo(s0, s1, co(nat0, cicc, nat1), co(nat0, cicc, nat1), co(cv(s0), cmul, cv(s1))))","pretty":"eqid((s0 ∈(0[[,]]1), s1 ∈(0[[,]]1)↦(s0[×]s1)))"},"body":{"origin":"|- wceq(cmpo(s0, s1, co(nat0, cicc, nat1), co(nat0, cicc, nat1), co(cv(s0), cmul, cv(s1))), cmpo(s0, s1, co(nat0, cicc, nat1), co(nat0, cicc, nat1), co(cv(s0), cmul, cv(s1))))","pretty":"⊢ (s0 ∈(0[[,]]1), s1 ∈(0[[,]]1)↦(s0[×]s1))=(s0 ∈(0[[,]]1), s1 ∈(0[[,]]1)↦(s0[×]s1))"},"cumulated":{"origin":"|- wcel(cmpo(s0, s1, co(nat0, cicc, nat1), co(nat0, cicc, nat1), co(cv(s0), cmul, cv(s1))), co(co(cii, ctx, cii), ccn, cii))\n-| wceq(co(co(cii, ctx, cii), ccn, cii), co(co(cii, ctx, cii), ccn, co(cfv(ctopn, ccnfld), crest, co(nat0, cicc, nat1))))\n-| wceq(cii, co(cfv(ctopn, ccnfld), crest, co(nat0, cicc, nat1)))\n-| diffss(s0, s1)\n-| diffsc(s0, co(nat0, cicc, nat1))\n-| diffsc(s0, cc)\n-| diffsc(s1, co(nat0, cicc, nat1))\n-| diffsc(s1, cc)\n-| wss(co(nat0, cicc, nat1), cc)\n-| diffsc(s0, cmul)\n-| diffsc(s1, cmul)\n-| wceq(cfv(ctopn, ccnfld), cfv(ctopn, ccnfld))\n-| wi(w3a(wcel(cfv(ctopn, ccnfld), cfv(ctopon, cc)), wss(crn(cmpo(s0, s1, co(nat0, cicc, nat1), co(nat0, cicc, nat1), co(cv(s0), cmul, cv(s1)))), co(nat0, cicc, nat1)), wss(co(nat0, cicc, nat1), cc)), wb(wcel(cmpo(s0, s1, co(nat0, cicc, nat1), co(nat0, cicc, nat1), co(cv(s0), cmul, cv(s1))), co(co(cii, ctx, cii), ccn, cfv(ctopn, ccnfld))), wcel(cmpo(s0, s1, co(nat0, cicc, nat1), co(nat0, cicc, nat1), co(cv(s0), cmul, cv(s1))), co(co(cii, ctx, cii), ccn, co(cfv(ctopn, ccnfld), crest, co(nat0, cicc, nat1))))))\n-| wi(wf(cmpo(s0, s1, co(nat0, cicc, nat1), co(nat0, cicc, nat1), co(cv(s0), cmul, cv(s1))), cxp(co(nat0, cicc, nat1), co(nat0, cicc, nat1)), co(nat0, cicc, nat1)), wss(crn(cmpo(s0, s1, co(nat0, cicc, nat1), co(nat0, cicc, nat1), co(cv(s0), cmul, cv(s1)))), co(nat0, cicc, nat1)))","pretty":"⊢ (s0 ∈(0[[,]]1), s1 ∈(0[[,]]1)↦(s0[×]s1))∈((II[tX]II)[Cn]II)\n⊣ ((II[tX]II)[Cn]II)=((II[tX]II)[Cn]((TopOpen ` CCfld)[|`t](0[[,]]1)))\n⊣ II =((TopOpen ` CCfld)[|`t](0[[,]]1))\n⊣ d(s0, s1)\n⊣ d(s0,(0[[,]]1))\n⊣ d(s0, ℂ)\n⊣ d(s1,(0[[,]]1))\n⊣ d(s1, ℂ)\n⊣ (0[[,]]1)⊆ ℂ\n⊣ d(s0, ×)\n⊣ d(s1, ×)\n⊣ (TopOpen ` CCfld)=(TopOpen ` CCfld)\n⊣ (((TopOpen ` CCfld)∈(TopOn ` ℂ)∧ ran((s0 ∈(0[[,]]1), s1 ∈(0[[,]]1)↦(s0[×]s1)))⊆(0[[,]]1)∧(0[[,]]1)⊆ ℂ)→((s0 ∈(0[[,]]1), s1 ∈(0[[,]]1)↦(s0[×]s1))∈((II[tX]II)[Cn](TopOpen ` CCfld))↔(s0 ∈(0[[,]]1), s1 ∈(0[[,]]1)↦(s0[×]s1))∈((II[tX]II)[Cn]((TopOpen ` CCfld)[|`t](0[[,]]1)))))\n⊣ (((s0 ∈(0[[,]]1), s1 ∈(0[[,]]1)↦(s0[×]s1)):((0[[,]]1)×(0[[,]]1))→(0[[,]]1))→ ran((s0 ∈(0[[,]]1), s1 ∈(0[[,]]1)↦(s0[×]s1)))⊆(0[[,]]1))"}},{"stmt":{"origin":"frn(cmpo(s0, s1, co(nat0, cicc, nat1), co(nat0, cicc, nat1), co(cv(s0), cmul, cv(s1))), cxp(co(nat0, cicc, nat1), co(nat0, cicc, nat1)), co(nat0, cicc, nat1))","pretty":"frn((s0 ∈(0[[,]]1), s1 ∈(0[[,]]1)↦(s0[×]s1)), ((0[[,]]1)×(0[[,]]1)), (0[[,]]1))"},"body":{"origin":"|- wi(wf(cmpo(s0, s1, co(nat0, cicc, nat1), co(nat0, cicc, nat1), co(cv(s0), cmul, cv(s1))), cxp(co(nat0, cicc, nat1), co(nat0, cicc, nat1)), co(nat0, cicc, nat1)), wss(crn(cmpo(s0, s1, co(nat0, cicc, nat1), co(nat0, cicc, nat1), co(cv(s0), cmul, cv(s1)))), co(nat0, cicc, nat1)))","pretty":"⊢ (((s0 ∈(0[[,]]1), s1 ∈(0[[,]]1)↦(s0[×]s1)):((0[[,]]1)×(0[[,]]1))→(0[[,]]1))→ ran((s0 ∈(0[[,]]1), s1 ∈(0[[,]]1)↦(s0[×]s1)))⊆(0[[,]]1))"},"cumulated":{"origin":"|- wcel(cmpo(s0, s1, co(nat0, cicc, nat1), co(nat0, cicc, nat1), co(cv(s0), cmul, cv(s1))), co(co(cii, ctx, cii), ccn, cii))\n-| wceq(co(co(cii, ctx, cii), ccn, cii), co(co(cii, ctx, cii), ccn, co(cfv(ctopn, ccnfld), crest, co(nat0, cicc, nat1))))\n-| wceq(cii, co(cfv(ctopn, ccnfld), crest, co(nat0, cicc, nat1)))\n-| diffss(s0, s1)\n-| diffsc(s0, co(nat0, cicc, nat1))\n-| diffsc(s0, cc)\n-| diffsc(s1, co(nat0, cicc, nat1))\n-| diffsc(s1, cc)\n-| wss(co(nat0, cicc, nat1), cc)\n-| diffsc(s0, cmul)\n-| diffsc(s1, cmul)\n-| wceq(cfv(ctopn, ccnfld), cfv(ctopn, ccnfld))\n-| wi(w3a(wcel(cfv(ctopn, ccnfld), cfv(ctopon, cc)), wss(crn(cmpo(s0, s1, co(nat0, cicc, nat1), co(nat0, cicc, nat1), co(cv(s0), cmul, cv(s1)))), co(nat0, cicc, nat1)), wss(co(nat0, cicc, nat1), cc)), wb(wcel(cmpo(s0, s1, co(nat0, cicc, nat1), co(nat0, cicc, nat1), co(cv(s0), cmul, cv(s1))), co(co(cii, ctx, cii), ccn, cfv(ctopn, ccnfld))), wcel(cmpo(s0, s1, co(nat0, cicc, nat1), co(nat0, cicc, nat1), co(cv(s0), cmul, cv(s1))), co(co(cii, ctx, cii), ccn, co(cfv(ctopn, ccnfld), crest, co(nat0, cicc, nat1))))))","pretty":"⊢ (s0 ∈(0[[,]]1), s1 ∈(0[[,]]1)↦(s0[×]s1))∈((II[tX]II)[Cn]II)\n⊣ ((II[tX]II)[Cn]II)=((II[tX]II)[Cn]((TopOpen ` CCfld)[|`t](0[[,]]1)))\n⊣ II =((TopOpen ` CCfld)[|`t](0[[,]]1))\n⊣ d(s0, s1)\n⊣ d(s0,(0[[,]]1))\n⊣ d(s0, ℂ)\n⊣ d(s1,(0[[,]]1))\n⊣ d(s1, ℂ)\n⊣ (0[[,]]1)⊆ ℂ\n⊣ d(s0, ×)\n⊣ d(s1, ×)\n⊣ (TopOpen ` CCfld)=(TopOpen ` CCfld)\n⊣ (((TopOpen ` CCfld)∈(TopOn ` ℂ)∧ ran((s0 ∈(0[[,]]1), s1 ∈(0[[,]]1)↦(s0[×]s1)))⊆(0[[,]]1)∧(0[[,]]1)⊆ ℂ)→((s0 ∈(0[[,]]1), s1 ∈(0[[,]]1)↦(s0[×]s1))∈((II[tX]II)[Cn](TopOpen ` CCfld))↔(s0 ∈(0[[,]]1), s1 ∈(0[[,]]1)↦(s0[×]s1))∈((II[tX]II)[Cn]((TopOpen ` CCfld)[|`t](0[[,]]1)))))"}},{"stmt":{"origin":"sstri(co(nat0, cicc, nat1), cc, cr)","pretty":"sstri((0[[,]]1), cc, cr)"},"body":{"origin":"|- wss(co(nat0, cicc, nat1), cc)\n-| wss(co(nat0, cicc, nat1), cr)\n-| wss(cr, cc)","pretty":"⊢ (0[[,]]1)⊆ ℂ\n⊣ (0[[,]]1)⊆ ℝ\n⊣ ℝ ⊆ ℂ"},"cumulated":{"origin":"|- wcel(cmpo(s0, s1, co(nat0, cicc, nat1), co(nat0, cicc, nat1), co(cv(s0), cmul, cv(s1))), co(co(cii, ctx, cii), ccn, cii))\n-| wceq(co(co(cii, ctx, cii), ccn, cii), co(co(cii, ctx, cii), ccn, co(cfv(ctopn, ccnfld), crest, co(nat0, cicc, nat1))))\n-| wceq(cii, co(cfv(ctopn, ccnfld), crest, co(nat0, cicc, nat1)))\n-| diffss(s0, s1)\n-| diffsc(s0, co(nat0, cicc, nat1))\n-| diffsc(s0, cc)\n-| diffsc(s1, co(nat0, cicc, nat1))\n-| diffsc(s1, cc)\n-| diffsc(s0, cmul)\n-| diffsc(s1, cmul)\n-| wceq(cfv(ctopn, ccnfld), cfv(ctopn, ccnfld))\n-| wi(w3a(wcel(cfv(ctopn, ccnfld), cfv(ctopon, cc)), wss(crn(cmpo(s0, s1, co(nat0, cicc, nat1), co(nat0, cicc, nat1), co(cv(s0), cmul, cv(s1)))), co(nat0, cicc, nat1)), wss(co(nat0, cicc, nat1), cc)), wb(wcel(cmpo(s0, s1, co(nat0, cicc, nat1), co(nat0, cicc, nat1), co(cv(s0), cmul, cv(s1))), co(co(cii, ctx, cii), ccn, cfv(ctopn, ccnfld))), wcel(cmpo(s0, s1, co(nat0, cicc, nat1), co(nat0, cicc, nat1), co(cv(s0), cmul, cv(s1))), co(co(cii, ctx, cii), ccn, co(cfv(ctopn, ccnfld), crest, co(nat0, cicc, nat1))))))\n-| wss(co(nat0, cicc, nat1), cr)\n-| wss(cr, cc)","pretty":"⊢ (s0 ∈(0[[,]]1), s1 ∈(0[[,]]1)↦(s0[×]s1))∈((II[tX]II)[Cn]II)\n⊣ ((II[tX]II)[Cn]II)=((II[tX]II)[Cn]((TopOpen ` CCfld)[|`t](0[[,]]1)))\n⊣ II =((TopOpen ` CCfld)[|`t](0[[,]]1))\n⊣ d(s0, s1)\n⊣ d(s0,(0[[,]]1))\n⊣ d(s0, ℂ)\n⊣ d(s1,(0[[,]]1))\n⊣ d(s1, ℂ)\n⊣ d(s0, ×)\n⊣ d(s1, ×)\n⊣ (TopOpen ` CCfld)=(TopOpen ` CCfld)\n⊣ (((TopOpen ` CCfld)∈(TopOn ` ℂ)∧ ran((s0 ∈(0[[,]]1), s1 ∈(0[[,]]1)↦(s0[×]s1)))⊆(0[[,]]1)∧(0[[,]]1)⊆ ℂ)→((s0 ∈(0[[,]]1), s1 ∈(0[[,]]1)↦(s0[×]s1))∈((II[tX]II)[Cn](TopOpen ` CCfld))↔(s0 ∈(0[[,]]1), s1 ∈(0[[,]]1)↦(s0[×]s1))∈((II[tX]II)[Cn]((TopOpen ` CCfld)[|`t](0[[,]]1)))))\n⊣ (0[[,]]1)⊆ ℝ\n⊣ ℝ ⊆ ℂ"}},{"stmt":{"origin":"unitssre()","pretty":"unitssre()"},"body":{"origin":"|- wss(co(nat0, cicc, nat1), cr)","pretty":"⊢ (0[[,]]1)⊆ ℝ"},"cumulated":{"origin":"|- wcel(cmpo(s0, s1, co(nat0, cicc, nat1), co(nat0, cicc, nat1), co(cv(s0), cmul, cv(s1))), co(co(cii, ctx, cii), ccn, cii))\n-| wceq(co(co(cii, ctx, cii), ccn, cii), co(co(cii, ctx, cii), ccn, co(cfv(ctopn, ccnfld), crest, co(nat0, cicc, nat1))))\n-| wceq(cii, co(cfv(ctopn, ccnfld), crest, co(nat0, cicc, nat1)))\n-| diffss(s0, s1)\n-| diffsc(s0, co(nat0, cicc, nat1))\n-| diffsc(s0, cc)\n-| diffsc(s1, co(nat0, cicc, nat1))\n-| diffsc(s1, cc)\n-| diffsc(s0, cmul)\n-| diffsc(s1, cmul)\n-| wceq(cfv(ctopn, ccnfld), cfv(ctopn, ccnfld))\n-| wi(w3a(wcel(cfv(ctopn, ccnfld), cfv(ctopon, cc)), wss(crn(cmpo(s0, s1, co(nat0, cicc, nat1), co(nat0, cicc, nat1), co(cv(s0), cmul, cv(s1)))), co(nat0, cicc, nat1)), wss(co(nat0, cicc, nat1), cc)), wb(wcel(cmpo(s0, s1, co(nat0, cicc, nat1), co(nat0, cicc, nat1), co(cv(s0), cmul, cv(s1))), co(co(cii, ctx, cii), ccn, cfv(ctopn, ccnfld))), wcel(cmpo(s0, s1, co(nat0, cicc, nat1), co(nat0, cicc, nat1), co(cv(s0), cmul, cv(s1))), co(co(cii, ctx, cii), ccn, co(cfv(ctopn, ccnfld), crest, co(nat0, cicc, nat1))))))\n-| wss(cr, cc)","pretty":"⊢ (s0 ∈(0[[,]]1), s1 ∈(0[[,]]1)↦(s0[×]s1))∈((II[tX]II)[Cn]II)\n⊣ ((II[tX]II)[Cn]II)=((II[tX]II)[Cn]((TopOpen ` CCfld)[|`t](0[[,]]1)))\n⊣ II =((TopOpen ` CCfld)[|`t](0[[,]]1))\n⊣ d(s0, s1)\n⊣ d(s0,(0[[,]]1))\n⊣ d(s0, ℂ)\n⊣ d(s1,(0[[,]]1))\n⊣ d(s1, ℂ)\n⊣ d(s0, ×)\n⊣ d(s1, ×)\n⊣ (TopOpen ` CCfld)=(TopOpen ` CCfld)\n⊣ (((TopOpen ` CCfld)∈(TopOn ` ℂ)∧ ran((s0 ∈(0[[,]]1), s1 ∈(0[[,]]1)↦(s0[×]s1)))⊆(0[[,]]1)∧(0[[,]]1)⊆ ℂ)→((s0 ∈(0[[,]]1), s1 ∈(0[[,]]1)↦(s0[×]s1))∈((II[tX]II)[Cn](TopOpen ` CCfld))↔(s0 ∈(0[[,]]1), s1 ∈(0[[,]]1)↦(s0[×]s1))∈((II[tX]II)[Cn]((TopOpen ` CCfld)[|`t](0[[,]]1)))))\n⊣ ℝ ⊆ ℂ"}},{"stmt":{"origin":"ax-resscn()","pretty":"ax-resscn()"},"body":{"origin":"|- wss(cr, cc)","pretty":"⊢ ℝ ⊆ ℂ"},"cumulated":{"origin":"|- wcel(cmpo(s0, s1, co(nat0, cicc, nat1), co(nat0, cicc, nat1), co(cv(s0), cmul, cv(s1))), co(co(cii, ctx, cii), ccn, cii))\n-| wceq(co(co(cii, ctx, cii), ccn, cii), co(co(cii, ctx, cii), ccn, co(cfv(ctopn, ccnfld), crest, co(nat0, cicc, nat1))))\n-| wceq(cii, co(cfv(ctopn, ccnfld), crest, co(nat0, cicc, nat1)))\n-| diffss(s0, s1)\n-| diffsc(s0, co(nat0, cicc, nat1))\n-| diffsc(s0, cc)\n-| diffsc(s1, co(nat0, cicc, nat1))\n-| diffsc(s1, cc)\n-| diffsc(s0, cmul)\n-| diffsc(s1, cmul)\n-| wceq(cfv(ctopn, ccnfld), cfv(ctopn, ccnfld))\n-| wi(w3a(wcel(cfv(ctopn, ccnfld), cfv(ctopon, cc)), wss(crn(cmpo(s0, s1, co(nat0, cicc, nat1), co(nat0, cicc, nat1), co(cv(s0), cmul, cv(s1)))), co(nat0, cicc, nat1)), wss(co(nat0, cicc, nat1), cc)), wb(wcel(cmpo(s0, s1, co(nat0, cicc, nat1), co(nat0, cicc, nat1), co(cv(s0), cmul, cv(s1))), co(co(cii, ctx, cii), ccn, cfv(ctopn, ccnfld))), wcel(cmpo(s0, s1, co(nat0, cicc, nat1), co(nat0, cicc, nat1), co(cv(s0), cmul, cv(s1))), co(co(cii, ctx, cii), ccn, co(cfv(ctopn, ccnfld), crest, co(nat0, cicc, nat1))))))","pretty":"⊢ (s0 ∈(0[[,]]1), s1 ∈(0[[,]]1)↦(s0[×]s1))∈((II[tX]II)[Cn]II)\n⊣ ((II[tX]II)[Cn]II)=((II[tX]II)[Cn]((TopOpen ` CCfld)[|`t](0[[,]]1)))\n⊣ II =((TopOpen ` CCfld)[|`t](0[[,]]1))\n⊣ d(s0, s1)\n⊣ d(s0,(0[[,]]1))\n⊣ d(s0, ℂ)\n⊣ d(s1,(0[[,]]1))\n⊣ d(s1, ℂ)\n⊣ d(s0, ×)\n⊣ d(s1, ×)\n⊣ (TopOpen ` CCfld)=(TopOpen ` CCfld)\n⊣ (((TopOpen ` CCfld)∈(TopOn ` ℂ)∧ ran((s0 ∈(0[[,]]1), s1 ∈(0[[,]]1)↦(s0[×]s1)))⊆(0[[,]]1)∧(0[[,]]1)⊆ ℂ)→((s0 ∈(0[[,]]1), s1 ∈(0[[,]]1)↦(s0[×]s1))∈((II[tX]II)[Cn](TopOpen ` CCfld))↔(s0 ∈(0[[,]]1), s1 ∈(0[[,]]1)↦(s0[×]s1))∈((II[tX]II)[Cn]((TopOpen ` CCfld)[|`t](0[[,]]1)))))"}},{"stmt":{"origin":"cnrest2(cfv(ctopn, ccnfld), cc, cmpo(s0, s1, co(nat0, cicc, nat1), co(nat0, cicc, nat1), co(cv(s0), cmul, cv(s1))), co(nat0, cicc, nat1), co(cii, ctx, cii))","pretty":"cnrest2((TopOpen ` CCfld), cc, (s0 ∈(0[[,]]1), s1 ∈(0[[,]]1)↦(s0[×]s1)), (0[[,]]1), (II[tX]II))"},"body":{"origin":"|- wi(w3a(wcel(cfv(ctopn, ccnfld), cfv(ctopon, cc)), wss(crn(cmpo(s0, s1, co(nat0, cicc, nat1), co(nat0, cicc, nat1), co(cv(s0), cmul, cv(s1)))), co(nat0, cicc, nat1)), wss(co(nat0, cicc, nat1), cc)), wb(wcel(cmpo(s0, s1, co(nat0, cicc, nat1), co(nat0, cicc, nat1), co(cv(s0), cmul, cv(s1))), co(co(cii, ctx, cii), ccn, cfv(ctopn, ccnfld))), wcel(cmpo(s0, s1, co(nat0, cicc, nat1), co(nat0, cicc, nat1), co(cv(s0), cmul, cv(s1))), co(co(cii, ctx, cii), ccn, co(cfv(ctopn, ccnfld), crest, co(nat0, cicc, nat1))))))","pretty":"⊢ (((TopOpen ` CCfld)∈(TopOn ` ℂ)∧ ran((s0 ∈(0[[,]]1), s1 ∈(0[[,]]1)↦(s0[×]s1)))⊆(0[[,]]1)∧(0[[,]]1)⊆ ℂ)→((s0 ∈(0[[,]]1), s1 ∈(0[[,]]1)↦(s0[×]s1))∈((II[tX]II)[Cn](TopOpen ` CCfld))↔(s0 ∈(0[[,]]1), s1 ∈(0[[,]]1)↦(s0[×]s1))∈((II[tX]II)[Cn]((TopOpen ` CCfld)[|`t](0[[,]]1)))))"},"cumulated":{"origin":"|- wcel(cmpo(s0, s1, co(nat0, cicc, nat1), co(nat0, cicc, nat1), co(cv(s0), cmul, cv(s1))), co(co(cii, ctx, cii), ccn, cii))\n-| wceq(co(co(cii, ctx, cii), ccn, cii), co(co(cii, ctx, cii), ccn, co(cfv(ctopn, ccnfld), crest, co(nat0, cicc, nat1))))\n-| wceq(cii, co(cfv(ctopn, ccnfld), crest, co(nat0, cicc, nat1)))\n-| diffss(s0, s1)\n-| diffsc(s0, co(nat0, cicc, nat1))\n-| diffsc(s0, cc)\n-| diffsc(s1, co(nat0, cicc, nat1))\n-| diffsc(s1, cc)\n-| diffsc(s0, cmul)\n-| diffsc(s1, cmul)\n-| wceq(cfv(ctopn, ccnfld), cfv(ctopn, ccnfld))","pretty":"⊢ (s0 ∈(0[[,]]1), s1 ∈(0[[,]]1)↦(s0[×]s1))∈((II[tX]II)[Cn]II)\n⊣ ((II[tX]II)[Cn]II)=((II[tX]II)[Cn]((TopOpen ` CCfld)[|`t](0[[,]]1)))\n⊣ II =((TopOpen ` CCfld)[|`t](0[[,]]1))\n⊣ d(s0, s1)\n⊣ d(s0,(0[[,]]1))\n⊣ d(s0, ℂ)\n⊣ d(s1,(0[[,]]1))\n⊣ d(s1, ℂ)\n⊣ d(s0, ×)\n⊣ d(s1, ×)\n⊣ (TopOpen ` CCfld)=(TopOpen ` CCfld)"}},{"stmt":{"origin":"oveq2i(co(cii, ctx, cii), ccn, cii, co(cfv(ctopn, ccnfld), crest, co(nat0, cicc, nat1)))","pretty":"oveq2i((II[tX]II), ccn, cii, ((TopOpen ` CCfld)[|`t](0[[,]]1)))"},"body":{"origin":"|- wceq(co(co(cii, ctx, cii), ccn, cii), co(co(cii, ctx, cii), ccn, co(cfv(ctopn, ccnfld), crest, co(nat0, cicc, nat1))))\n-| wceq(cii, co(cfv(ctopn, ccnfld), crest, co(nat0, cicc, nat1)))","pretty":"⊢ ((II[tX]II)[Cn]II)=((II[tX]II)[Cn]((TopOpen ` CCfld)[|`t](0[[,]]1)))\n⊣ II =((TopOpen ` CCfld)[|`t](0[[,]]1))"},"cumulated":{"origin":"|- wcel(cmpo(s0, s1, co(nat0, cicc, nat1), co(nat0, cicc, nat1), co(cv(s0), cmul, cv(s1))), co(co(cii, ctx, cii), ccn, cii))\n-| wceq(cii, co(cfv(ctopn, ccnfld), crest, co(nat0, cicc, nat1)))\n-| diffss(s0, s1)\n-| diffsc(s0, co(nat0, cicc, nat1))\n-| diffsc(s0, cc)\n-| diffsc(s1, co(nat0, cicc, nat1))\n-| diffsc(s1, cc)\n-| diffsc(s0, cmul)\n-| diffsc(s1, cmul)\n-| wceq(cfv(ctopn, ccnfld), cfv(ctopn, ccnfld))","pretty":"⊢ (s0 ∈(0[[,]]1), s1 ∈(0[[,]]1)↦(s0[×]s1))∈((II[tX]II)[Cn]II)\n⊣ II =((TopOpen ` CCfld)[|`t](0[[,]]1))\n⊣ d(s0, s1)\n⊣ d(s0,(0[[,]]1))\n⊣ d(s0, ℂ)\n⊣ d(s1,(0[[,]]1))\n⊣ d(s1, ℂ)\n⊣ d(s0, ×)\n⊣ d(s1, ×)\n⊣ (TopOpen ` CCfld)=(TopOpen ` CCfld)"}},{"stmt":{"origin":"dfii3(cfv(ctopn, ccnfld))","pretty":"dfii3((TopOpen ` CCfld))"},"body":{"origin":"|- wceq(cii, co(cfv(ctopn, ccnfld), crest, co(nat0, cicc, nat1)))\n-| wceq(cfv(ctopn, ccnfld), cfv(ctopn, ccnfld))","pretty":"⊢ II =((TopOpen ` CCfld)[|`t](0[[,]]1))\n⊣ (TopOpen ` CCfld)=(TopOpen ` CCfld)"},"cumulated":{"origin":"|- wcel(cmpo(s0, s1, co(nat0, cicc, nat1), co(nat0, cicc, nat1), co(cv(s0), cmul, cv(s1))), co(co(cii, ctx, cii), ccn, cii))\n-| diffss(s0, s1)\n-| diffsc(s0, co(nat0, cicc, nat1))\n-| diffsc(s0, cc)\n-| diffsc(s1, co(nat0, cicc, nat1))\n-| diffsc(s1, cc)\n-| diffsc(s0, cmul)\n-| diffsc(s1, cmul)\n-| wceq(cfv(ctopn, ccnfld), cfv(ctopn, ccnfld))","pretty":"⊢ (s0 ∈(0[[,]]1), s1 ∈(0[[,]]1)↦(s0[×]s1))∈((II[tX]II)[Cn]II)\n⊣ d(s0, s1)\n⊣ d(s0,(0[[,]]1))\n⊣ d(s0, ℂ)\n⊣ d(s1,(0[[,]]1))\n⊣ d(s1, ℂ)\n⊣ d(s0, ×)\n⊣ d(s1, ×)\n⊣ (TopOpen ` CCfld)=(TopOpen ` CCfld)"}},{"stmt":{"origin":"eqid(cfv(ctopn, ccnfld))","pretty":"eqid((TopOpen ` CCfld))"},"body":{"origin":"|- wceq(cfv(ctopn, ccnfld), cfv(ctopn, ccnfld))","pretty":"⊢ (TopOpen ` CCfld)=(TopOpen ` CCfld)"},"cumulated":{"origin":"|- wcel(cmpo(s0, s1, co(nat0, cicc, nat1), co(nat0, cicc, nat1), co(cv(s0), cmul, cv(s1))), co(co(cii, ctx, cii), ccn, cii))\n-| diffss(s0, s1)\n-| diffsc(s0, co(nat0, cicc, nat1))\n-| diffsc(s0, cc)\n-| diffsc(s1, co(nat0, cicc, nat1))\n-| diffsc(s1, cc)\n-| diffsc(s0, cmul)\n-| diffsc(s1, cmul)","pretty":"⊢ (s0 ∈(0[[,]]1), s1 ∈(0[[,]]1)↦(s0[×]s1))∈((II[tX]II)[Cn]II)\n⊣ d(s0, s1)\n⊣ d(s0,(0[[,]]1))\n⊣ d(s0, ℂ)\n⊣ d(s1,(0[[,]]1))\n⊣ d(s1, ℂ)\n⊣ d(s0, ×)\n⊣ d(s1, ×)"}},{"stmt":{"origin":"diff.co.s(s0, nat0, cicc, nat1)","pretty":"diff.co.s(s0, nat0, cicc, nat1)"},"body":{"origin":"|- diffsc(s0, co(nat0, cicc, nat1))\n-| diffsc(s0, nat0)\n-| diffsc(s0, cicc)\n-| diffsc(s0, nat1)","pretty":"⊢ d(s0,(0[[,]]1))\n⊣ d(s0, 0)\n⊣ d(s0,[,])\n⊣ d(s0, 1)"},"cumulated":{"origin":"|- wcel(cmpo(s0, s1, co(nat0, cicc, nat1), co(nat0, cicc, nat1), co(cv(s0), cmul, cv(s1))), co(co(cii, ctx, cii), ccn, cii))\n-| diffss(s0, s1)\n-| diffsc(s0, cc)\n-| diffsc(s1, co(nat0, cicc, nat1))\n-| diffsc(s1, cc)\n-| diffsc(s0, cmul)\n-| diffsc(s1, cmul)\n-| diffsc(s0, nat0)\n-| diffsc(s0, cicc)\n-| diffsc(s0, nat1)","pretty":"⊢ (s0 ∈(0[[,]]1), s1 ∈(0[[,]]1)↦(s0[×]s1))∈((II[tX]II)[Cn]II)\n⊣ d(s0, s1)\n⊣ d(s0, ℂ)\n⊣ d(s1,(0[[,]]1))\n⊣ d(s1, ℂ)\n⊣ d(s0, ×)\n⊣ d(s1, ×)\n⊣ d(s0, 0)\n⊣ d(s0,[,])\n⊣ d(s0, 1)"}},{"stmt":{"origin":"diff.nat0.s(s0)","pretty":"diff.nat0.s(s0)"},"body":{"origin":"|- diffsc(s0, nat0)","pretty":"⊢ d(s0, 0)"},"cumulated":{"origin":"|- wcel(cmpo(s0, s1, co(nat0, cicc, nat1), co(nat0, cicc, nat1), co(cv(s0), cmul, cv(s1))), co(co(cii, ctx, cii), ccn, cii))\n-| diffss(s0, s1)\n-| diffsc(s0, cc)\n-| diffsc(s1, co(nat0, cicc, nat1))\n-| diffsc(s1, cc)\n-| diffsc(s0, cmul)\n-| diffsc(s1, cmul)\n-| diffsc(s0, cicc)\n-| diffsc(s0, nat1)","pretty":"⊢ (s0 ∈(0[[,]]1), s1 ∈(0[[,]]1)↦(s0[×]s1))∈((II[tX]II)[Cn]II)\n⊣ d(s0, s1)\n⊣ d(s0, ℂ)\n⊣ d(s1,(0[[,]]1))\n⊣ d(s1, ℂ)\n⊣ d(s0, ×)\n⊣ d(s1, ×)\n⊣ d(s0,[,])\n⊣ d(s0, 1)"}},{"stmt":{"origin":"diff.cicc.s(s0)","pretty":"diff.cicc.s(s0)"},"body":{"origin":"|- diffsc(s0, cicc)","pretty":"⊢ d(s0,[,])"},"cumulated":{"origin":"|- wcel(cmpo(s0, s1, co(nat0, cicc, nat1), co(nat0, cicc, nat1), co(cv(s0), cmul, cv(s1))), co(co(cii, ctx, cii), ccn, cii))\n-| diffss(s0, s1)\n-| diffsc(s0, cc)\n-| diffsc(s1, co(nat0, cicc, nat1))\n-| diffsc(s1, cc)\n-| diffsc(s0, cmul)\n-| diffsc(s1, cmul)\n-| diffsc(s0, nat1)","pretty":"⊢ (s0 ∈(0[[,]]1), s1 ∈(0[[,]]1)↦(s0[×]s1))∈((II[tX]II)[Cn]II)\n⊣ d(s0, s1)\n⊣ d(s0, ℂ)\n⊣ d(s1,(0[[,]]1))\n⊣ d(s1, ℂ)\n⊣ d(s0, ×)\n⊣ d(s1, ×)\n⊣ d(s0, 1)"}},{"stmt":{"origin":"diff.nat1.s(s0)","pretty":"diff.nat1.s(s0)"},"body":{"origin":"|- diffsc(s0, nat1)","pretty":"⊢ d(s0, 1)"},"cumulated":{"origin":"|- wcel(cmpo(s0, s1, co(nat0, cicc, nat1), co(nat0, cicc, nat1), co(cv(s0), cmul, cv(s1))), co(co(cii, ctx, cii), ccn, cii))\n-| diffss(s0, s1)\n-| diffsc(s0, cc)\n-| diffsc(s1, co(nat0, cicc, nat1))\n-| diffsc(s1, cc)\n-| diffsc(s0, cmul)\n-| diffsc(s1, cmul)","pretty":"⊢ (s0 ∈(0[[,]]1), s1 ∈(0[[,]]1)↦(s0[×]s1))∈((II[tX]II)[Cn]II)\n⊣ d(s0, s1)\n⊣ d(s0, ℂ)\n⊣ d(s1,(0[[,]]1))\n⊣ d(s1, ℂ)\n⊣ d(s0, ×)\n⊣ d(s1, ×)"}},{"stmt":{"origin":"diff.cc.s(s0)","pretty":"diff.cc.s(s0)"},"body":{"origin":"|- diffsc(s0, cc)","pretty":"⊢ d(s0, ℂ)"},"cumulated":{"origin":"|- wcel(cmpo(s0, s1, co(nat0, cicc, nat1), co(nat0, cicc, nat1), co(cv(s0), cmul, cv(s1))), co(co(cii, ctx, cii), ccn, cii))\n-| diffss(s0, s1)\n-| diffsc(s1, co(nat0, cicc, nat1))\n-| diffsc(s1, cc)\n-| diffsc(s0, cmul)\n-| diffsc(s1, cmul)","pretty":"⊢ (s0 ∈(0[[,]]1), s1 ∈(0[[,]]1)↦(s0[×]s1))∈((II[tX]II)[Cn]II)\n⊣ d(s0, s1)\n⊣ d(s1,(0[[,]]1))\n⊣ d(s1, ℂ)\n⊣ d(s0, ×)\n⊣ d(s1, ×)"}},{"stmt":{"origin":"diff.co.s(s1, nat0, cicc, nat1)","pretty":"diff.co.s(s1, nat0, cicc, nat1)"},"body":{"origin":"|- diffsc(s1, co(nat0, cicc, nat1))\n-| diffsc(s1, nat0)\n-| diffsc(s1, cicc)\n-| diffsc(s1, nat1)","pretty":"⊢ d(s1,(0[[,]]1))\n⊣ d(s1, 0)\n⊣ d(s1,[,])\n⊣ d(s1, 1)"},"cumulated":{"origin":"|- wcel(cmpo(s0, s1, co(nat0, cicc, nat1), co(nat0, cicc, nat1), co(cv(s0), cmul, cv(s1))), co(co(cii, ctx, cii), ccn, cii))\n-| diffss(s0, s1)\n-| diffsc(s1, cc)\n-| diffsc(s0, cmul)\n-| diffsc(s1, cmul)\n-| diffsc(s1, nat0)\n-| diffsc(s1, cicc)\n-| diffsc(s1, nat1)","pretty":"⊢ (s0 ∈(0[[,]]1), s1 ∈(0[[,]]1)↦(s0[×]s1))∈((II[tX]II)[Cn]II)\n⊣ d(s0, s1)\n⊣ d(s1, ℂ)\n⊣ d(s0, ×)\n⊣ d(s1, ×)\n⊣ d(s1, 0)\n⊣ d(s1,[,])\n⊣ d(s1, 1)"}},{"stmt":{"origin":"diff.nat0.s(s1)","pretty":"diff.nat0.s(s1)"},"body":{"origin":"|- diffsc(s1, nat0)","pretty":"⊢ d(s1, 0)"},"cumulated":{"origin":"|- wcel(cmpo(s0, s1, co(nat0, cicc, nat1), co(nat0, cicc, nat1), co(cv(s0), cmul, cv(s1))), co(co(cii, ctx, cii), ccn, cii))\n-| diffss(s0, s1)\n-| diffsc(s1, cc)\n-| diffsc(s0, cmul)\n-| diffsc(s1, cmul)\n-| diffsc(s1, cicc)\n-| diffsc(s1, nat1)","pretty":"⊢ (s0 ∈(0[[,]]1), s1 ∈(0[[,]]1)↦(s0[×]s1))∈((II[tX]II)[Cn]II)\n⊣ d(s0, s1)\n⊣ d(s1, ℂ)\n⊣ d(s0, ×)\n⊣ d(s1, ×)\n⊣ d(s1,[,])\n⊣ d(s1, 1)"}},{"stmt":{"origin":"diff.cicc.s(s1)","pretty":"diff.cicc.s(s1)"},"body":{"origin":"|- diffsc(s1, cicc)","pretty":"⊢ d(s1,[,])"},"cumulated":{"origin":"|- wcel(cmpo(s0, s1, co(nat0, cicc, nat1), co(nat0, cicc, nat1), co(cv(s0), cmul, cv(s1))), co(co(cii, ctx, cii), ccn, cii))\n-| diffss(s0, s1)\n-| diffsc(s1, cc)\n-| diffsc(s0, cmul)\n-| diffsc(s1, cmul)\n-| diffsc(s1, nat1)","pretty":"⊢ (s0 ∈(0[[,]]1), s1 ∈(0[[,]]1)↦(s0[×]s1))∈((II[tX]II)[Cn]II)\n⊣ d(s0, s1)\n⊣ d(s1, ℂ)\n⊣ d(s0, ×)\n⊣ d(s1, ×)\n⊣ d(s1, 1)"}},{"stmt":{"origin":"diff.nat1.s(s1)","pretty":"diff.nat1.s(s1)"},"body":{"origin":"|- diffsc(s1, nat1)","pretty":"⊢ d(s1, 1)"},"cumulated":{"origin":"|- wcel(cmpo(s0, s1, co(nat0, cicc, nat1), co(nat0, cicc, nat1), co(cv(s0), cmul, cv(s1))), co(co(cii, ctx, cii), ccn, cii))\n-| diffss(s0, s1)\n-| diffsc(s1, cc)\n-| diffsc(s0, cmul)\n-| diffsc(s1, cmul)","pretty":"⊢ (s0 ∈(0[[,]]1), s1 ∈(0[[,]]1)↦(s0[×]s1))∈((II[tX]II)[Cn]II)\n⊣ d(s0, s1)\n⊣ d(s1, ℂ)\n⊣ d(s0, ×)\n⊣ d(s1, ×)"}},{"stmt":{"origin":"diff.cc.s(s1)","pretty":"diff.cc.s(s1)"},"body":{"origin":"|- diffsc(s1, cc)","pretty":"⊢ d(s1, ℂ)"},"cumulated":{"origin":"|- wcel(cmpo(s0, s1, co(nat0, cicc, nat1), co(nat0, cicc, nat1), co(cv(s0), cmul, cv(s1))), co(co(cii, ctx, cii), ccn, cii))\n-| diffss(s0, s1)\n-| diffsc(s0, cmul)\n-| diffsc(s1, cmul)","pretty":"⊢ (s0 ∈(0[[,]]1), s1 ∈(0[[,]]1)↦(s0[×]s1))∈((II[tX]II)[Cn]II)\n⊣ d(s0, s1)\n⊣ d(s0, ×)\n⊣ d(s1, ×)"}},{"stmt":{"origin":"diff.cmul.s(s0)","pretty":"diff.cmul.s(s0)"},"body":{"origin":"|- diffsc(s0, cmul)","pretty":"⊢ d(s0, ×)"},"cumulated":{"origin":"|- wcel(cmpo(s0, s1, co(nat0, cicc, nat1), co(nat0, cicc, nat1), co(cv(s0), cmul, cv(s1))), co(co(cii, ctx, cii), ccn, cii))\n-| diffss(s0, s1)\n-| diffsc(s1, cmul)","pretty":"⊢ (s0 ∈(0[[,]]1), s1 ∈(0[[,]]1)↦(s0[×]s1))∈((II[tX]II)[Cn]II)\n⊣ d(s0, s1)\n⊣ d(s1, ×)"}},{"stmt":{"origin":"diff.cmul.s(s1)","pretty":"diff.cmul.s(s1)"},"body":{"origin":"|- diffsc(s1, cmul)","pretty":"⊢ d(s1, ×)"},"cumulated":{"origin":"|- wcel(cmpo(s0, s1, co(nat0, cicc, nat1), co(nat0, cicc, nat1), co(cv(s0), cmul, cv(s1))), co(co(cii, ctx, cii), ccn, cii))\n-| diffss(s0, s1)","pretty":"⊢ (s0 ∈(0[[,]]1), s1 ∈(0[[,]]1)↦(s0[×]s1))∈((II[tX]II)[Cn]II)\n⊣ d(s0, s1)"}}],"comment":"Multiplication is a continuous function on the unit interval. (Contributed by Mario Carneiro, 8-Jun-2014.)","parent":["eleqtrri","mpbi","mptru","cnmpt2res","a1i","eqeltrri","ax-mp","ax-mulf","ffn","fnov","mulcn","mp3an","cnfldtopon","rgen2a","iimulcl","sylbi","fmpt2","eqid","frn","sstri","unitssre","ax-resscn","cnrest2","oveq2i","dfii3","diff.co.s","diff.nat0.s","diff.cicc.s","diff.nat1.s","diff.cc.s","diff.cmul.s"],"children":["pcorevlem"]}